{"userId":172,"recommendations":[{"ISBN":8014,"rating":5.387486},{"ISBN":9566,"rating":5.328326},{"ISBN":8403,"rating":5.3040023},{"ISBN":9534,"rating":5.241868},{"ISBN":6971,"rating":5.230854},{"ISBN":3628,"rating":5.197861},{"ISBN":7988,"rating":5.1728144},{"ISBN":9110,"rating":5.1477294},{"ISBN":6590,"rating":5.1126394},{"ISBN":8548,"rating":5.108972}]}
{"userId":562,"recommendations":[{"ISBN":8255,"rating":6.589394},{"ISBN":7662,"rating":6.4404454},{"ISBN":9815,"rating":6.327128},{"ISBN":5730,"rating":6.1839933},{"ISBN":7135,"rating":6.16363},{"ISBN":9516,"rating":6.073195},{"ISBN":5189,"rating":6.021851},{"ISBN":4220,"rating":5.975235},{"ISBN":7438,"rating":5.9685173},{"ISBN":9623,"rating":5.96116}]}
{"userId":716,"recommendations":[{"ISBN":9345,"rating":6.2447624},{"ISBN":7844,"rating":5.8874755},{"ISBN":8580,"rating":5.651368},{"ISBN":7039,"rating":5.4994187},{"ISBN":9624,"rating":5.4829707},{"ISBN":7661,"rating":5.4669614},{"ISBN":8498,"rating":5.434541},{"ISBN":4755,"rating":5.424441},{"ISBN":4475,"rating":5.41682},{"ISBN":6572,"rating":5.4030247}]}
{"userId":864,"recommendations":[{"ISBN":9011,"rating":5.5770607},{"ISBN":8276,"rating":5.4776487},{"ISBN":7837,"rating":5.2976155},{"ISBN":6120,"rating":5.215528},{"ISBN":8882,"rating":5.1650004},{"ISBN":8965,"rating":5.1361256},{"ISBN":9578,"rating":5.104049},{"ISBN":9908,"rating":5.0820966},{"ISBN":7242,"rating":5.0563507},{"ISBN":8326,"rating":5.050248}]}
{"userId":1054,"recommendations":[{"ISBN":8271,"rating":6.4803843},{"ISBN":9884,"rating":6.2695055},{"ISBN":4715,"rating":6.2421327},{"ISBN":9932,"rating":6.219729},{"ISBN":9492,"rating":6.1060824},{"ISBN":2100,"rating":6.0523906},{"ISBN":9374,"rating":6.052157},{"ISBN":8703,"rating":6.0427933},{"ISBN":9181,"rating":5.994888},{"ISBN":6008,"rating":5.9877667}]}
{"userId":1429,"recommendations":[{"ISBN":4154,"rating":5.966691},{"ISBN":1338,"rating":5.678643},{"ISBN":9076,"rating":5.4848948},{"ISBN":5208,"rating":5.3981085},{"ISBN":4868,"rating":5.2377515},{"ISBN":6543,"rating":5.1921196},{"ISBN":2236,"rating":5.153732},{"ISBN":7844,"rating":5.060653},{"ISBN":464,"rating":5.0323286},{"ISBN":4778,"rating":5.01571}]}
{"userId":1776,"recommendations":[{"ISBN":7844,"rating":6.456174},{"ISBN":9792,"rating":6.4455647},{"ISBN":4606,"rating":6.315551},{"ISBN":9008,"rating":6.210561},{"ISBN":7762,"rating":6.1597996},{"ISBN":8284,"rating":6.119902},{"ISBN":9294,"rating":6.119293},{"ISBN":6027,"rating":6.083923},{"ISBN":9158,"rating":6.083646},{"ISBN":9980,"rating":6.0718446}]}
{"userId":1891,"recommendations":[{"ISBN":9260,"rating":4.918509},{"ISBN":8601,"rating":4.8553762},{"ISBN":8882,"rating":4.694934},{"ISBN":8948,"rating":4.632577},{"ISBN":8479,"rating":4.609367},{"ISBN":9709,"rating":4.5836163},{"ISBN":7837,"rating":4.5783696},{"ISBN":7440,"rating":4.5559177},{"ISBN":7457,"rating":4.45482},{"ISBN":8276,"rating":4.398145}]}
{"userId":1948,"recommendations":[{"ISBN":9932,"rating":5.956706},{"ISBN":5059,"rating":5.772673},{"ISBN":8200,"rating":5.577213},{"ISBN":6570,"rating":5.5563097},{"ISBN":7337,"rating":5.548463},{"ISBN":9322,"rating":5.486669},{"ISBN":9203,"rating":5.444903},{"ISBN":8875,"rating":5.434563},{"ISBN":5784,"rating":5.431454},{"ISBN":3491,"rating":5.4208155}]}
{"userId":1999,"recommendations":[{"ISBN":6605,"rating":6.5226374},{"ISBN":9624,"rating":6.263689},{"ISBN":5977,"rating":6.2397933},{"ISBN":8964,"rating":6.2230115},{"ISBN":8611,"rating":6.205056},{"ISBN":8233,"rating":6.183051},{"ISBN":7496,"rating":6.1710863},{"ISBN":8403,"rating":6.1616154},{"ISBN":6220,"rating":6.118894},{"ISBN":9553,"rating":6.113611}]}
{"userId":2215,"recommendations":[{"ISBN":9505,"rating":6.5313015},{"ISBN":9769,"rating":6.055472},{"ISBN":6543,"rating":5.880159},{"ISBN":8519,"rating":5.8793344},{"ISBN":9978,"rating":5.8068895},{"ISBN":7869,"rating":5.679725},{"ISBN":6102,"rating":5.6365333},{"ISBN":9329,"rating":5.5795355},{"ISBN":7947,"rating":5.5023136},{"ISBN":6962,"rating":5.491371}]}
{"userId":2282,"recommendations":[{"ISBN":9322,"rating":5.464324},{"ISBN":9008,"rating":5.213309},{"ISBN":6583,"rating":4.8466463},{"ISBN":9294,"rating":4.768913},{"ISBN":7844,"rating":4.7423267},{"ISBN":8854,"rating":4.7205825},{"ISBN":9932,"rating":4.7048063},{"ISBN":9347,"rating":4.6937504},{"ISBN":4606,"rating":4.687153},{"ISBN":5454,"rating":4.683855}]}
{"userId":2381,"recommendations":[{"ISBN":7337,"rating":7.0957355},{"ISBN":7837,"rating":6.8992705},{"ISBN":9011,"rating":6.831523},{"ISBN":8882,"rating":6.751268},{"ISBN":5059,"rating":6.5142674},{"ISBN":8014,"rating":6.4878483},{"ISBN":8326,"rating":6.4844055},{"ISBN":9709,"rating":6.466781},{"ISBN":6948,"rating":6.3503237},{"ISBN":8224,"rating":6.2362456}]}
{"userId":2900,"recommendations":[{"ISBN":4154,"rating":6.1058216},{"ISBN":8479,"rating":5.87962},{"ISBN":8948,"rating":5.876808},{"ISBN":9260,"rating":5.8744526},{"ISBN":8601,"rating":5.7438803},{"ISBN":5208,"rating":5.737659},{"ISBN":9534,"rating":5.735794},{"ISBN":8946,"rating":5.695338},{"ISBN":8548,"rating":5.6931014},{"ISBN":1338,"rating":5.682578}]}
{"userId":2969,"recommendations":[{"ISBN":9962,"rating":6.390625},{"ISBN":8999,"rating":6.3809943},{"ISBN":9992,"rating":6.3199024},{"ISBN":1657,"rating":6.295651},{"ISBN":8498,"rating":6.250262},{"ISBN":5730,"rating":6.066187},{"ISBN":6586,"rating":6.032663},{"ISBN":8547,"rating":6.0209093},{"ISBN":9884,"rating":5.9857106},{"ISBN":8259,"rating":5.9617567}]}
{"userId":3055,"recommendations":[{"ISBN":9709,"rating":5.118536},{"ISBN":8601,"rating":4.8986907},{"ISBN":7837,"rating":4.852615},{"ISBN":7337,"rating":4.819949},{"ISBN":9578,"rating":4.778221},{"ISBN":7110,"rating":4.7758055},{"ISBN":7039,"rating":4.7410665},{"ISBN":7881,"rating":4.688446},{"ISBN":8948,"rating":4.6183195},{"ISBN":8580,"rating":4.6133766}]}
{"userId":3057,"recommendations":[{"ISBN":5529,"rating":5.9479346},{"ISBN":8601,"rating":5.594611},{"ISBN":8948,"rating":5.432215},{"ISBN":4202,"rating":5.3874755},{"ISBN":9460,"rating":5.386108},{"ISBN":6924,"rating":5.3175945},{"ISBN":7798,"rating":5.297387},{"ISBN":7496,"rating":5.2943673},{"ISBN":3898,"rating":5.2833133},{"ISBN":6620,"rating":5.2496696}]}
{"userId":3555,"recommendations":[{"ISBN":8948,"rating":6.065796},{"ISBN":8601,"rating":5.970821},{"ISBN":8580,"rating":5.8508},{"ISBN":6240,"rating":5.742123},{"ISBN":9790,"rating":5.705841},{"ISBN":6615,"rating":5.6748085},{"ISBN":9345,"rating":5.60318},{"ISBN":8875,"rating":5.5623503},{"ISBN":4157,"rating":5.557231},{"ISBN":3821,"rating":5.4897914}]}
{"userId":3837,"recommendations":[{"ISBN":9214,"rating":6.6532674},{"ISBN":7844,"rating":6.576487},{"ISBN":8948,"rating":6.5626993},{"ISBN":8479,"rating":6.417897},{"ISBN":7971,"rating":6.2222977},{"ISBN":8601,"rating":6.1919127},{"ISBN":9458,"rating":6.08909},{"ISBN":7440,"rating":6.050062},{"ISBN":7337,"rating":6.03669},{"ISBN":9505,"rating":5.921384}]}
{"userId":4179,"recommendations":[{"ISBN":9505,"rating":5.43217},{"ISBN":9732,"rating":4.909968},{"ISBN":7881,"rating":4.661135},{"ISBN":7009,"rating":4.5194273},{"ISBN":5727,"rating":4.4788585},{"ISBN":8014,"rating":4.478266},{"ISBN":7789,"rating":4.459779},{"ISBN":7117,"rating":4.4519277},{"ISBN":9910,"rating":4.4340067},{"ISBN":8934,"rating":4.4098067}]}
{"userId":4732,"recommendations":[{"ISBN":8601,"rating":6.628559},{"ISBN":8233,"rating":5.4424763},{"ISBN":8238,"rating":5.441902},{"ISBN":9540,"rating":5.3781714},{"ISBN":7495,"rating":5.3422227},{"ISBN":8964,"rating":5.3210306},{"ISBN":9578,"rating":5.293477},{"ISBN":9576,"rating":5.265828},{"ISBN":4336,"rating":5.240545},{"ISBN":6435,"rating":5.23963}]}
{"userId":5073,"recommendations":[{"ISBN":9992,"rating":5.3816705},{"ISBN":9962,"rating":5.261329},{"ISBN":8559,"rating":5.2314086},{"ISBN":8882,"rating":4.989234},{"ISBN":9110,"rating":4.981648},{"ISBN":7039,"rating":4.9696317},{"ISBN":6586,"rating":4.7900453},{"ISBN":7147,"rating":4.783365},{"ISBN":6160,"rating":4.749876},{"ISBN":9891,"rating":4.7449956}]}
{"userId":5250,"recommendations":[{"ISBN":9624,"rating":4.8540697},{"ISBN":8403,"rating":4.735734},{"ISBN":8519,"rating":4.68022},{"ISBN":8964,"rating":4.621748},{"ISBN":9505,"rating":4.6108727},{"ISBN":7401,"rating":4.56991},{"ISBN":6600,"rating":4.5690184},{"ISBN":6084,"rating":4.56846},{"ISBN":8580,"rating":4.566967},{"ISBN":9439,"rating":4.566474}]}
{"userId":5616,"recommendations":[{"ISBN":7844,"rating":5.1987786},{"ISBN":9505,"rating":4.9959908},{"ISBN":6989,"rating":4.9737854},{"ISBN":8276,"rating":4.899433},{"ISBN":9509,"rating":4.8852234},{"ISBN":8732,"rating":4.8113933},{"ISBN":7191,"rating":4.7896},{"ISBN":5335,"rating":4.77653},{"ISBN":9294,"rating":4.7739396},{"ISBN":9329,"rating":4.7616377}]}
{"userId":5665,"recommendations":[{"ISBN":7337,"rating":6.749001},{"ISBN":8875,"rating":6.515667},{"ISBN":8948,"rating":6.304383},{"ISBN":7837,"rating":6.210503},{"ISBN":9790,"rating":6.1929727},{"ISBN":9709,"rating":6.191789},{"ISBN":8703,"rating":5.9641347},{"ISBN":5454,"rating":5.955006},{"ISBN":5325,"rating":5.8841057},{"ISBN":9246,"rating":5.8712}]}
{"userId":5837,"recommendations":[{"ISBN":6522,"rating":5.7132306},{"ISBN":8854,"rating":5.6017013},{"ISBN":5102,"rating":5.5513396},{"ISBN":6224,"rating":5.5058737},{"ISBN":9492,"rating":5.5016775},{"ISBN":8113,"rating":5.439252},{"ISBN":6158,"rating":5.3483925},{"ISBN":5543,"rating":5.158537},{"ISBN":8661,"rating":5.1129527},{"ISBN":7739,"rating":5.0488844}]}
{"userId":5863,"recommendations":[{"ISBN":8601,"rating":5.11705},{"ISBN":5306,"rating":5.031295},{"ISBN":9110,"rating":4.9405947},{"ISBN":8259,"rating":4.930071},{"ISBN":5707,"rating":4.8939757},{"ISBN":9290,"rating":4.878627},{"ISBN":7496,"rating":4.815224},{"ISBN":9946,"rating":4.7816424},{"ISBN":3488,"rating":4.7631645},{"ISBN":9516,"rating":4.718938}]}
{"userId":6104,"recommendations":[{"ISBN":6312,"rating":5.810277},{"ISBN":7507,"rating":5.7624383},{"ISBN":3224,"rating":5.700096},{"ISBN":5848,"rating":5.651739},{"ISBN":3502,"rating":5.6409926},{"ISBN":7849,"rating":5.6341376},{"ISBN":8429,"rating":5.6019845},{"ISBN":8352,"rating":5.5704093},{"ISBN":4943,"rating":5.5637465},{"ISBN":7282,"rating":5.552607}]}
{"userId":6699,"recommendations":[{"ISBN":7844,"rating":6.1374736},{"ISBN":9260,"rating":5.594855},{"ISBN":8479,"rating":5.5408716},{"ISBN":9553,"rating":5.5161114},{"ISBN":9345,"rating":5.471638},{"ISBN":8358,"rating":5.438717},{"ISBN":8276,"rating":5.4263325},{"ISBN":9010,"rating":5.347762},{"ISBN":9843,"rating":5.3470726},{"ISBN":6915,"rating":5.3301024}]}
{"userId":6828,"recommendations":[{"ISBN":9980,"rating":5.5921063},{"ISBN":8239,"rating":5.4738264},{"ISBN":9850,"rating":5.456233},{"ISBN":3224,"rating":5.449361},{"ISBN":9158,"rating":5.357423},{"ISBN":7560,"rating":5.3473825},{"ISBN":9492,"rating":5.334841},{"ISBN":6681,"rating":5.3139386},{"ISBN":9534,"rating":5.299665},{"ISBN":7871,"rating":5.295173}]}
{"userId":6930,"recommendations":[{"ISBN":9260,"rating":5.569913},{"ISBN":7039,"rating":5.5219064},{"ISBN":8559,"rating":5.4849353},{"ISBN":8479,"rating":5.398915},{"ISBN":9709,"rating":5.3666587},{"ISBN":8948,"rating":5.333672},{"ISBN":7844,"rating":5.249658},{"ISBN":9345,"rating":5.124682},{"ISBN":6077,"rating":5.09902},{"ISBN":9441,"rating":5.0452094}]}
{"userId":6972,"recommendations":[{"ISBN":9732,"rating":5.209921},{"ISBN":5208,"rating":5.0015783},{"ISBN":1338,"rating":4.9921446},{"ISBN":9534,"rating":4.9902186},{"ISBN":4154,"rating":4.9094915},{"ISBN":2236,"rating":4.8759847},{"ISBN":4868,"rating":4.8061104},{"ISBN":5653,"rating":4.788663},{"ISBN":6543,"rating":4.748403},{"ISBN":7401,"rating":4.733492}]}
{"userId":7224,"recommendations":[{"ISBN":8056,"rating":5.004933},{"ISBN":7254,"rating":4.926671},{"ISBN":8978,"rating":4.817983},{"ISBN":6920,"rating":4.8074965},{"ISBN":1788,"rating":4.8046007},{"ISBN":5207,"rating":4.803257},{"ISBN":9932,"rating":4.8027573},{"ISBN":6876,"rating":4.7987385},{"ISBN":5580,"rating":4.789682},{"ISBN":3628,"rating":4.7890587}]}
{"userId":7364,"recommendations":[{"ISBN":9214,"rating":6.3335648},{"ISBN":8498,"rating":5.6654525},{"ISBN":8259,"rating":5.5631514},{"ISBN":1729,"rating":5.4131346},{"ISBN":8653,"rating":5.4053288},{"ISBN":8948,"rating":5.3897734},{"ISBN":1198,"rating":5.3159957},{"ISBN":6077,"rating":5.236272},{"ISBN":3502,"rating":5.1806974},{"ISBN":287,"rating":5.1599884}]}
{"userId":7498,"recommendations":[{"ISBN":3224,"rating":5.8265014},{"ISBN":5454,"rating":5.2384243},{"ISBN":5325,"rating":5.206702},{"ISBN":8875,"rating":5.1464},{"ISBN":9214,"rating":5.1078577},{"ISBN":6712,"rating":5.0478783},{"ISBN":2439,"rating":5.0309176},{"ISBN":7871,"rating":5.015535},{"ISBN":6555,"rating":4.926414},{"ISBN":8827,"rating":4.8888683}]}
{"userId":7527,"recommendations":[{"ISBN":9322,"rating":6.328241},{"ISBN":7844,"rating":5.9169683},{"ISBN":6769,"rating":5.9009895},{"ISBN":8519,"rating":5.8782744},{"ISBN":9347,"rating":5.870196},{"ISBN":7789,"rating":5.8415856},{"ISBN":4962,"rating":5.833148},{"ISBN":8170,"rating":5.7962284},{"ISBN":5454,"rating":5.7872577},{"ISBN":9008,"rating":5.779334}]}
{"userId":7822,"recommendations":[{"ISBN":7537,"rating":5.8363767},{"ISBN":9076,"rating":5.754396},{"ISBN":7496,"rating":5.7471566},{"ISBN":9891,"rating":5.6846695},{"ISBN":9992,"rating":5.6835446},{"ISBN":7756,"rating":5.669683},{"ISBN":9912,"rating":5.6509323},{"ISBN":9110,"rating":5.613166},{"ISBN":7844,"rating":5.6077423},{"ISBN":4154,"rating":5.604988}]}
{"userId":8048,"recommendations":[{"ISBN":9677,"rating":6.7902555},{"ISBN":7800,"rating":6.783834},{"ISBN":4606,"rating":6.7661967},{"ISBN":6216,"rating":6.7532206},{"ISBN":9792,"rating":6.440192},{"ISBN":5291,"rating":6.428423},{"ISBN":4783,"rating":6.3819394},{"ISBN":5454,"rating":6.3576407},{"ISBN":4991,"rating":6.3180614},{"ISBN":8239,"rating":6.3109226}]}
{"userId":8101,"recommendations":[{"ISBN":3502,"rating":6.0673614},{"ISBN":6031,"rating":5.829394},{"ISBN":9732,"rating":5.80939},{"ISBN":9714,"rating":5.797936},{"ISBN":8522,"rating":5.664758},{"ISBN":7249,"rating":5.5794916},{"ISBN":5418,"rating":5.5415187},{"ISBN":3815,"rating":5.4509554},{"ISBN":6401,"rating":5.4194307},{"ISBN":6865,"rating":5.410889}]}
{"userId":8920,"recommendations":[{"ISBN":9505,"rating":5.319715},{"ISBN":4411,"rating":4.5549355},{"ISBN":8948,"rating":4.4844723},{"ISBN":6543,"rating":4.470349},{"ISBN":7337,"rating":4.42662},{"ISBN":8013,"rating":4.411702},{"ISBN":7529,"rating":4.4108753},{"ISBN":9769,"rating":4.3915577},{"ISBN":8817,"rating":4.352595},{"ISBN":7995,"rating":4.346888}]}
{"userId":9050,"recommendations":[{"ISBN":5208,"rating":5.8737226},{"ISBN":9732,"rating":5.8649817},{"ISBN":7844,"rating":5.644419},{"ISBN":4344,"rating":5.503772},{"ISBN":4778,"rating":5.452443},{"ISBN":9008,"rating":5.406306},{"ISBN":8374,"rating":5.379207},{"ISBN":2236,"rating":5.355977},{"ISBN":8933,"rating":5.3523507},{"ISBN":5418,"rating":5.34108}]}
{"userId":9897,"recommendations":[{"ISBN":9932,"rating":6.159752},{"ISBN":8326,"rating":5.8547077},{"ISBN":6120,"rating":5.7828927},{"ISBN":8056,"rating":5.6930227},{"ISBN":8946,"rating":5.6641026},{"ISBN":7648,"rating":5.569396},{"ISBN":6784,"rating":5.5528626},{"ISBN":9578,"rating":5.51567},{"ISBN":9908,"rating":5.5011706},{"ISBN":5784,"rating":5.492664}]}
{"userId":9978,"recommendations":[{"ISBN":9345,"rating":5.6816993},{"ISBN":8580,"rating":5.645638},{"ISBN":9624,"rating":5.593817},{"ISBN":7844,"rating":5.53291},{"ISBN":8498,"rating":5.4959884},{"ISBN":5804,"rating":5.4547625},{"ISBN":8547,"rating":5.426162},{"ISBN":8999,"rating":5.3899384},{"ISBN":9997,"rating":5.3763504},{"ISBN":1657,"rating":5.3589272}]}
{"userId":10071,"recommendations":[{"ISBN":8548,"rating":5.741825},{"ISBN":8220,"rating":5.6919007},{"ISBN":9553,"rating":5.662221},{"ISBN":6605,"rating":5.6569314},{"ISBN":9123,"rating":5.538129},{"ISBN":7401,"rating":5.4830008},{"ISBN":9534,"rating":5.454112},{"ISBN":9842,"rating":5.4352045},{"ISBN":7754,"rating":5.426423},{"ISBN":8611,"rating":5.3304315}]}
{"userId":10076,"recommendations":[{"ISBN":5845,"rating":7.466359},{"ISBN":9762,"rating":7.0454383},{"ISBN":9001,"rating":6.879797},{"ISBN":9283,"rating":6.613826},{"ISBN":9551,"rating":6.479223},{"ISBN":2638,"rating":6.4672947},{"ISBN":9518,"rating":6.3630795},{"ISBN":8573,"rating":6.315813},{"ISBN":8548,"rating":6.089571},{"ISBN":4919,"rating":6.0750275}]}
{"userId":10324,"recommendations":[{"ISBN":9505,"rating":6.067996},{"ISBN":9618,"rating":5.639839},{"ISBN":9686,"rating":5.461137},{"ISBN":4518,"rating":5.296523},{"ISBN":5059,"rating":5.2607527},{"ISBN":9402,"rating":5.258161},{"ISBN":9071,"rating":5.2255483},{"ISBN":9404,"rating":5.1926017},{"ISBN":8888,"rating":5.1432266},{"ISBN":8368,"rating":5.129376}]}
{"userId":10437,"recommendations":[{"ISBN":9505,"rating":7.401034},{"ISBN":6543,"rating":7.080036},{"ISBN":1935,"rating":7.045835},{"ISBN":7995,"rating":6.9095817},{"ISBN":8338,"rating":6.8253202},{"ISBN":4940,"rating":6.7188697},{"ISBN":9472,"rating":6.656033},{"ISBN":8365,"rating":6.617951},{"ISBN":6962,"rating":6.589953},{"ISBN":8368,"rating":6.56501}]}
{"userId":10546,"recommendations":[{"ISBN":7844,"rating":6.268231},{"ISBN":9624,"rating":5.921141},{"ISBN":9345,"rating":5.653691},{"ISBN":5373,"rating":5.579357},{"ISBN":8095,"rating":5.501266},{"ISBN":8479,"rating":5.4194613},{"ISBN":9553,"rating":5.3114777},{"ISBN":9243,"rating":5.2887125},{"ISBN":9317,"rating":5.2818003},{"ISBN":7440,"rating":5.235079}]}
{"userId":10730,"recommendations":[{"ISBN":9505,"rating":5.037087},{"ISBN":9208,"rating":4.954523},{"ISBN":7876,"rating":4.944328},{"ISBN":8519,"rating":4.8464637},{"ISBN":9534,"rating":4.8086257},{"ISBN":7947,"rating":4.804716},{"ISBN":9119,"rating":4.79862},{"ISBN":6971,"rating":4.7814727},{"ISBN":8403,"rating":4.781099},{"ISBN":5376,"rating":4.7747154}]}
{"userId":10783,"recommendations":[{"ISBN":4154,"rating":8.195006},{"ISBN":1935,"rating":7.7487855},{"ISBN":1338,"rating":7.4209},{"ISBN":9260,"rating":7.0139227},{"ISBN":9379,"rating":6.992251},{"ISBN":6893,"rating":6.9164276},{"ISBN":5778,"rating":6.784107},{"ISBN":9942,"rating":6.749565},{"ISBN":7130,"rating":6.746094},{"ISBN":3479,"rating":6.726659}]}
{"userId":10809,"recommendations":[{"ISBN":9732,"rating":6.796496},{"ISBN":5953,"rating":6.2731752},{"ISBN":9980,"rating":6.1571774},{"ISBN":7849,"rating":6.0253496},{"ISBN":7507,"rating":5.9196463},{"ISBN":9792,"rating":5.9062624},{"ISBN":3815,"rating":5.8436627},{"ISBN":255,"rating":5.838449},{"ISBN":3420,"rating":5.814297},{"ISBN":5208,"rating":5.759705}]}
{"userId":11157,"recommendations":[{"ISBN":9732,"rating":5.3153553},{"ISBN":7844,"rating":5.1093545},{"ISBN":7947,"rating":5.049035},{"ISBN":7039,"rating":5.0378532},{"ISBN":4154,"rating":5.0312004},{"ISBN":5208,"rating":5.022645},{"ISBN":1338,"rating":5.008979},{"ISBN":8580,"rating":4.986589},{"ISBN":464,"rating":4.901245},{"ISBN":9076,"rating":4.8808484}]}
{"userId":11268,"recommendations":[{"ISBN":9505,"rating":5.902167},{"ISBN":8519,"rating":5.897395},{"ISBN":8747,"rating":5.6670127},{"ISBN":9418,"rating":5.5804095},{"ISBN":5059,"rating":5.526787},{"ISBN":8601,"rating":5.446064},{"ISBN":7876,"rating":5.440902},{"ISBN":7844,"rating":5.3921623},{"ISBN":7789,"rating":5.283522},{"ISBN":3582,"rating":5.26376}]}
{"userId":11486,"recommendations":[{"ISBN":9505,"rating":6.232048},{"ISBN":8519,"rating":5.802576},{"ISBN":9831,"rating":5.5937095},{"ISBN":7789,"rating":5.533503},{"ISBN":6084,"rating":5.5252123},{"ISBN":7844,"rating":5.516693},{"ISBN":9328,"rating":5.502164},{"ISBN":8403,"rating":5.4741325},{"ISBN":7876,"rating":5.4728174},{"ISBN":9262,"rating":5.432589}]}
{"userId":11643,"recommendations":[{"ISBN":9214,"rating":6.1503835},{"ISBN":7844,"rating":5.9263597},{"ISBN":9158,"rating":5.815741},{"ISBN":8948,"rating":5.7779255},{"ISBN":9798,"rating":5.696421},{"ISBN":9534,"rating":5.623535},{"ISBN":8479,"rating":5.604793},{"ISBN":7560,"rating":5.5709267},{"ISBN":7988,"rating":5.539945},{"ISBN":7457,"rating":5.4916296}]}
{"userId":11774,"recommendations":[{"ISBN":4509,"rating":5.39053},{"ISBN":3581,"rating":5.2929115},{"ISBN":7496,"rating":5.203515},{"ISBN":9506,"rating":5.144577},{"ISBN":8224,"rating":5.141533},{"ISBN":3482,"rating":5.1341653},{"ISBN":1121,"rating":5.0528207},{"ISBN":7416,"rating":5.040578},{"ISBN":3508,"rating":5.034054},{"ISBN":3321,"rating":4.986729}]}
{"userId":11813,"recommendations":[{"ISBN":9008,"rating":5.773068},{"ISBN":9119,"rating":5.618541},{"ISBN":4962,"rating":5.5592637},{"ISBN":9214,"rating":5.5115414},{"ISBN":3502,"rating":5.392553},{"ISBN":7736,"rating":5.337335},{"ISBN":6031,"rating":5.3349404},{"ISBN":9865,"rating":5.3348813},{"ISBN":4739,"rating":5.3228865},{"ISBN":8641,"rating":5.3110175}]}
{"userId":12159,"recommendations":[{"ISBN":9516,"rating":5.28651},{"ISBN":8946,"rating":5.170348},{"ISBN":8548,"rating":5.1436577},{"ISBN":9815,"rating":5.093588},{"ISBN":5435,"rating":5.0692515},{"ISBN":6639,"rating":5.0494485},{"ISBN":7662,"rating":5.0421495},{"ISBN":7963,"rating":4.980564},{"ISBN":4262,"rating":4.9615917},{"ISBN":9679,"rating":4.948627}]}
{"userId":12240,"recommendations":[{"ISBN":9534,"rating":6.588228},{"ISBN":4154,"rating":6.4542503},{"ISBN":7369,"rating":6.3052526},{"ISBN":9815,"rating":6.2431407},{"ISBN":1935,"rating":6.201948},{"ISBN":1338,"rating":5.984815},{"ISBN":3479,"rating":5.9374294},{"ISBN":9169,"rating":5.8906856},{"ISBN":5778,"rating":5.8845663},{"ISBN":7871,"rating":5.7303157}]}
{"userId":12413,"recommendations":[{"ISBN":9158,"rating":5.2643776},{"ISBN":8636,"rating":5.1396465},{"ISBN":9479,"rating":5.062953},{"ISBN":9884,"rating":4.8186812},{"ISBN":8239,"rating":4.815176},{"ISBN":7844,"rating":4.7464375},{"ISBN":8479,"rating":4.6726456},{"ISBN":9356,"rating":4.6155553},{"ISBN":9317,"rating":4.569681},{"ISBN":7002,"rating":4.563385}]}
{"userId":12732,"recommendations":[{"ISBN":7871,"rating":7.026551},{"ISBN":8382,"rating":6.06808},{"ISBN":9492,"rating":5.8772516},{"ISBN":3224,"rating":5.858894},{"ISBN":8368,"rating":5.851975},{"ISBN":7369,"rating":5.7551885},{"ISBN":5778,"rating":5.7460093},{"ISBN":2928,"rating":5.7289743},{"ISBN":9548,"rating":5.662372},{"ISBN":6224,"rating":5.6085653}]}
{"userId":12733,"recommendations":[{"ISBN":9260,"rating":6.070729},{"ISBN":6893,"rating":5.794613},{"ISBN":9516,"rating":5.667163},{"ISBN":6599,"rating":5.658788},{"ISBN":4154,"rating":5.6380305},{"ISBN":5208,"rating":5.5887513},{"ISBN":9169,"rating":5.535283},{"ISBN":4595,"rating":5.462823},{"ISBN":4150,"rating":5.440973},{"ISBN":8292,"rating":5.362916}]}
{"userId":13445,"recommendations":[{"ISBN":9492,"rating":5.3129134},{"ISBN":4154,"rating":4.915786},{"ISBN":7871,"rating":4.8493752},{"ISBN":6224,"rating":4.841338},{"ISBN":1338,"rating":4.729643},{"ISBN":6414,"rating":4.694066},{"ISBN":8854,"rating":4.661176},{"ISBN":9193,"rating":4.6425247},{"ISBN":7165,"rating":4.629774},{"ISBN":9307,"rating":4.6268454}]}
{"userId":13472,"recommendations":[{"ISBN":8946,"rating":4.9378257},{"ISBN":2100,"rating":4.912722},{"ISBN":8882,"rating":4.842101},{"ISBN":7337,"rating":4.7388573},{"ISBN":8948,"rating":4.7090006},{"ISBN":5435,"rating":4.708086},{"ISBN":9578,"rating":4.691647},{"ISBN":6018,"rating":4.681299},{"ISBN":5258,"rating":4.6733284},{"ISBN":8703,"rating":4.6488633}]}
{"userId":13473,"recommendations":[{"ISBN":9732,"rating":9.343612},{"ISBN":9910,"rating":7.7824507},{"ISBN":5727,"rating":7.7208495},{"ISBN":9997,"rating":7.6609387},{"ISBN":7315,"rating":7.4610753},{"ISBN":8170,"rating":7.3827944},{"ISBN":9219,"rating":7.307334},{"ISBN":464,"rating":7.1488295},{"ISBN":9624,"rating":7.137613},{"ISBN":2236,"rating":7.105903}]}
{"userId":13530,"recommendations":[{"ISBN":8948,"rating":10.821423},{"ISBN":2701,"rating":9.5380125},{"ISBN":7798,"rating":9.523903},{"ISBN":9790,"rating":9.3689785},{"ISBN":5529,"rating":9.274585},{"ISBN":7482,"rating":9.264394},{"ISBN":7449,"rating":9.258578},{"ISBN":2458,"rating":8.787586},{"ISBN":2399,"rating":8.77031},{"ISBN":9214,"rating":8.769959}]}
{"userId":13539,"recommendations":[{"ISBN":8165,"rating":5.5551805},{"ISBN":8891,"rating":5.143075},{"ISBN":8875,"rating":5.010452},{"ISBN":6937,"rating":4.962724},{"ISBN":8200,"rating":4.901324},{"ISBN":9967,"rating":4.88647},{"ISBN":9561,"rating":4.8715515},{"ISBN":9129,"rating":4.834715},{"ISBN":5046,"rating":4.8164134},{"ISBN":9779,"rating":4.774448}]}
{"userId":13733,"recommendations":[{"ISBN":9324,"rating":6.843339},{"ISBN":8113,"rating":6.647304},{"ISBN":5851,"rating":6.6136923},{"ISBN":9008,"rating":6.6054544},{"ISBN":8879,"rating":6.478961},{"ISBN":8505,"rating":6.403734},{"ISBN":9498,"rating":6.2130184},{"ISBN":9320,"rating":6.1556735},{"ISBN":4798,"rating":6.118622},{"ISBN":7756,"rating":6.1055903}]}
{"userId":13839,"recommendations":[{"ISBN":9008,"rating":6.1123624},{"ISBN":6312,"rating":5.777556},{"ISBN":9439,"rating":5.695596},{"ISBN":8522,"rating":5.6366577},{"ISBN":8639,"rating":5.5746484},{"ISBN":7424,"rating":5.5368047},{"ISBN":7736,"rating":5.4434037},{"ISBN":9374,"rating":5.437225},{"ISBN":8673,"rating":5.412762},{"ISBN":5256,"rating":5.391729}]}
{"userId":13893,"recommendations":[{"ISBN":8946,"rating":4.9472494},{"ISBN":8238,"rating":4.8399067},{"ISBN":9815,"rating":4.8294024},{"ISBN":3628,"rating":4.814912},{"ISBN":9578,"rating":4.790935},{"ISBN":8978,"rating":4.7757053},{"ISBN":6317,"rating":4.7225275},{"ISBN":9842,"rating":4.711606},{"ISBN":8415,"rating":4.702841},{"ISBN":9110,"rating":4.6834326}]}
{"userId":14384,"recommendations":[{"ISBN":8014,"rating":5.9640484},{"ISBN":8326,"rating":5.9545946},{"ISBN":6120,"rating":5.804055},{"ISBN":9932,"rating":5.745781},{"ISBN":8882,"rating":5.6522737},{"ISBN":9008,"rating":5.630843},{"ISBN":6920,"rating":5.6248393},{"ISBN":3628,"rating":5.607795},{"ISBN":8013,"rating":5.604978},{"ISBN":9024,"rating":5.5951715}]}
{"userId":14418,"recommendations":[{"ISBN":9516,"rating":5.31236},{"ISBN":8807,"rating":5.211431},{"ISBN":3502,"rating":4.987268},{"ISBN":9850,"rating":4.94176},{"ISBN":7507,"rating":4.8746405},{"ISBN":8663,"rating":4.863574},{"ISBN":6642,"rating":4.8239093},{"ISBN":5038,"rating":4.8134427},{"ISBN":862,"rating":4.803855},{"ISBN":7871,"rating":4.7833953}]}
{"userId":14427,"recommendations":[{"ISBN":9482,"rating":6.1885405},{"ISBN":7229,"rating":6.1480746},{"ISBN":9505,"rating":6.038189},{"ISBN":5038,"rating":6.0132093},{"ISBN":8003,"rating":5.98178},{"ISBN":3060,"rating":5.92266},{"ISBN":8512,"rating":5.9109926},{"ISBN":2891,"rating":5.903902},{"ISBN":7871,"rating":5.885611},{"ISBN":3624,"rating":5.8839045}]}
{"userId":14650,"recommendations":[{"ISBN":8113,"rating":7.252882},{"ISBN":9732,"rating":6.6895},{"ISBN":9131,"rating":6.640826},{"ISBN":6810,"rating":6.3402276},{"ISBN":6158,"rating":6.318304},{"ISBN":4809,"rating":6.306694},{"ISBN":5584,"rating":6.2856307},{"ISBN":5653,"rating":6.2594705},{"ISBN":7025,"rating":6.161909},{"ISBN":1338,"rating":6.114332}]}
{"userId":14723,"recommendations":[{"ISBN":1338,"rating":7.028019},{"ISBN":4154,"rating":7.010805},{"ISBN":9076,"rating":6.553532},{"ISBN":6543,"rating":6.386218},{"ISBN":1935,"rating":6.2211843},{"ISBN":9732,"rating":6.196671},{"ISBN":464,"rating":6.1549845},{"ISBN":2236,"rating":6.1326437},{"ISBN":5208,"rating":6.025549},{"ISBN":9934,"rating":5.921704}]}
{"userId":14936,"recommendations":[{"ISBN":5845,"rating":5.8535056},{"ISBN":9003,"rating":5.8349257},{"ISBN":6032,"rating":5.8061786},{"ISBN":9534,"rating":5.6649017},{"ISBN":8548,"rating":5.611918},{"ISBN":9032,"rating":5.495596},{"ISBN":8220,"rating":5.403048},{"ISBN":7736,"rating":5.3863254},{"ISBN":6965,"rating":5.3109527},{"ISBN":9997,"rating":5.3021564}]}
{"userId":15015,"recommendations":[{"ISBN":9008,"rating":6.7728696},{"ISBN":8239,"rating":6.6192718},{"ISBN":9677,"rating":6.5486817},{"ISBN":4663,"rating":6.3583207},{"ISBN":9932,"rating":6.3534784},{"ISBN":4783,"rating":6.3317213},{"ISBN":8639,"rating":6.2485366},{"ISBN":6096,"rating":6.241673},{"ISBN":9322,"rating":6.2367964},{"ISBN":5454,"rating":6.2242155}]}
{"userId":15321,"recommendations":[{"ISBN":9732,"rating":5.957729},{"ISBN":7507,"rating":5.411245},{"ISBN":7581,"rating":5.3461633},{"ISBN":9714,"rating":5.338586},{"ISBN":6312,"rating":5.2212367},{"ISBN":8352,"rating":5.1733475},{"ISBN":5012,"rating":5.168964},{"ISBN":7515,"rating":5.1589737},{"ISBN":7193,"rating":5.1438503},{"ISBN":862,"rating":5.1342735}]}
{"userId":15499,"recommendations":[{"ISBN":8703,"rating":8.315025},{"ISBN":8271,"rating":8.1971445},{"ISBN":4715,"rating":7.5670614},{"ISBN":7337,"rating":7.533241},{"ISBN":9246,"rating":7.440684},{"ISBN":6639,"rating":7.408098},{"ISBN":2100,"rating":7.1844893},{"ISBN":9516,"rating":7.124835},{"ISBN":6008,"rating":7.099932},{"ISBN":8255,"rating":7.0870323}]}
{"userId":15517,"recommendations":[{"ISBN":8875,"rating":6.301613},{"ISBN":7337,"rating":6.2630296},{"ISBN":7837,"rating":5.956064},{"ISBN":8601,"rating":5.827766},{"ISBN":8200,"rating":5.823221},{"ISBN":9578,"rating":5.7878823},{"ISBN":5325,"rating":5.7197003},{"ISBN":7037,"rating":5.7107997},{"ISBN":6241,"rating":5.668145},{"ISBN":5531,"rating":5.658655}]}
{"userId":15744,"recommendations":[{"ISBN":6583,"rating":6.4972677},{"ISBN":9322,"rating":6.3208137},{"ISBN":7401,"rating":6.2386274},{"ISBN":7844,"rating":6.154693},{"ISBN":8519,"rating":6.03063},{"ISBN":9978,"rating":6.025921},{"ISBN":8548,"rating":5.9962463},{"ISBN":6032,"rating":5.9760695},{"ISBN":9003,"rating":5.9463854},{"ISBN":7947,"rating":5.934057}]}
{"userId":15848,"recommendations":[{"ISBN":8601,"rating":6.131419},{"ISBN":8807,"rating":5.2993617},{"ISBN":9214,"rating":5.295223},{"ISBN":7947,"rating":5.2661695},{"ISBN":9208,"rating":5.228218},{"ISBN":5212,"rating":5.213145},{"ISBN":7871,"rating":5.1871824},{"ISBN":9714,"rating":5.159752},{"ISBN":9566,"rating":5.156987},{"ISBN":255,"rating":5.1564765}]}
{"userId":16008,"recommendations":[{"ISBN":8875,"rating":6.023604},{"ISBN":6570,"rating":5.9543824},{"ISBN":9492,"rating":5.930532},{"ISBN":7129,"rating":5.695585},{"ISBN":9768,"rating":5.6486855},{"ISBN":9790,"rating":5.645661},{"ISBN":7337,"rating":5.637855},{"ISBN":8513,"rating":5.615312},{"ISBN":6712,"rating":5.599048},{"ISBN":7837,"rating":5.5963717}]}
{"userId":16030,"recommendations":[{"ISBN":6312,"rating":5.427891},{"ISBN":9208,"rating":5.3385577},{"ISBN":8403,"rating":5.2697835},{"ISBN":8014,"rating":5.2619224},{"ISBN":9502,"rating":5.239902},{"ISBN":7424,"rating":5.226462},{"ISBN":6971,"rating":5.2232447},{"ISBN":9732,"rating":5.152954},{"ISBN":5524,"rating":5.1521893},{"ISBN":7239,"rating":5.1507792}]}
{"userId":16166,"recommendations":[{"ISBN":6583,"rating":5.1027102},{"ISBN":8548,"rating":5.082338},{"ISBN":9932,"rating":4.999083},{"ISBN":5784,"rating":4.8949633},{"ISBN":8877,"rating":4.8622947},{"ISBN":7754,"rating":4.8609934},{"ISBN":9322,"rating":4.8464937},{"ISBN":7401,"rating":4.81074},{"ISBN":9842,"rating":4.773361},{"ISBN":3628,"rating":4.772473}]}
{"userId":16313,"recommendations":[{"ISBN":9214,"rating":7.359733},{"ISBN":6240,"rating":5.791533},{"ISBN":3821,"rating":5.7224383},{"ISBN":4962,"rating":5.575016},{"ISBN":9458,"rating":5.562618},{"ISBN":744,"rating":5.5611234},{"ISBN":8479,"rating":5.5517325},{"ISBN":8601,"rating":5.545869},{"ISBN":7971,"rating":5.495813},{"ISBN":6798,"rating":5.3516827}]}
{"userId":16392,"recommendations":[{"ISBN":9815,"rating":6.666077},{"ISBN":9932,"rating":6.29658},{"ISBN":8548,"rating":6.1559277},{"ISBN":8946,"rating":6.1033034},{"ISBN":8056,"rating":6.0633936},{"ISBN":5784,"rating":6.0491004},{"ISBN":3628,"rating":6.021794},{"ISBN":8978,"rating":5.976449},{"ISBN":5435,"rating":5.9377375},{"ISBN":4898,"rating":5.9152045}]}
{"userId":16670,"recommendations":[{"ISBN":5059,"rating":6.2512918},{"ISBN":6570,"rating":5.990541},{"ISBN":9119,"rating":5.543656},{"ISBN":5623,"rating":5.501577},{"ISBN":8617,"rating":5.4990234},{"ISBN":9203,"rating":5.4169483},{"ISBN":8181,"rating":5.404696},{"ISBN":7337,"rating":5.3934093},{"ISBN":7500,"rating":5.373579},{"ISBN":8200,"rating":5.3340297}]}
{"userId":17344,"recommendations":[{"ISBN":1935,"rating":6.6597004},{"ISBN":6120,"rating":6.0332384},{"ISBN":9392,"rating":5.9466667},{"ISBN":9815,"rating":5.8112607},{"ISBN":9398,"rating":5.7730904},{"ISBN":9516,"rating":5.746362},{"ISBN":8056,"rating":5.690592},{"ISBN":9932,"rating":5.66368},{"ISBN":8014,"rating":5.513943},{"ISBN":8326,"rating":5.505412}]}
{"userId":17494,"recommendations":[{"ISBN":8854,"rating":6.4171786},{"ISBN":9008,"rating":6.117387},{"ISBN":6712,"rating":5.865471},{"ISBN":9932,"rating":5.804675},{"ISBN":9119,"rating":5.753221},{"ISBN":6583,"rating":5.7277966},{"ISBN":8639,"rating":5.7067027},{"ISBN":6522,"rating":5.6874924},{"ISBN":4107,"rating":5.672472},{"ISBN":6570,"rating":5.656664}]}
{"userId":17611,"recommendations":[{"ISBN":9320,"rating":6.5250072},{"ISBN":4202,"rating":6.4987593},{"ISBN":8907,"rating":6.4982667},{"ISBN":9432,"rating":6.411315},{"ISBN":9992,"rating":6.34964},{"ISBN":8165,"rating":6.322219},{"ISBN":9516,"rating":6.316841},{"ISBN":5992,"rating":6.2518115},{"ISBN":9110,"rating":6.251766},{"ISBN":9600,"rating":6.1520066}]}
{"userId":17917,"recommendations":[{"ISBN":9418,"rating":6.59775},{"ISBN":8519,"rating":6.311522},{"ISBN":8747,"rating":6.2485046},{"ISBN":6937,"rating":6.061279},{"ISBN":7876,"rating":5.975318},{"ISBN":6605,"rating":5.947515},{"ISBN":9505,"rating":5.929434},{"ISBN":7200,"rating":5.8389673},{"ISBN":5059,"rating":5.812003},{"ISBN":7754,"rating":5.7973366}]}
{"userId":18109,"recommendations":[{"ISBN":8882,"rating":4.8663282},{"ISBN":5435,"rating":4.70601},{"ISBN":9992,"rating":4.7034235},{"ISBN":8946,"rating":4.6231093},{"ISBN":9516,"rating":4.6112905},{"ISBN":8056,"rating":4.5780706},{"ISBN":8559,"rating":4.53035},{"ISBN":9110,"rating":4.528095},{"ISBN":9962,"rating":4.49281},{"ISBN":8326,"rating":4.489072}]}
{"userId":18562,"recommendations":[{"ISBN":6712,"rating":6.0808506},{"ISBN":9505,"rating":5.8191605},{"ISBN":7881,"rating":5.7400255},{"ISBN":8512,"rating":5.574602},{"ISBN":6613,"rating":5.5551033},{"ISBN":5454,"rating":5.546618},{"ISBN":3224,"rating":5.5216513},{"ISBN":7129,"rating":5.5004606},{"ISBN":9686,"rating":5.497822},{"ISBN":6570,"rating":5.434471}]}
{"userId":18937,"recommendations":[{"ISBN":5454,"rating":7.046732},{"ISBN":8875,"rating":6.90368},{"ISBN":5325,"rating":6.575405},{"ISBN":8794,"rating":6.4333105},{"ISBN":9790,"rating":6.4198484},{"ISBN":8239,"rating":6.398623},{"ISBN":4783,"rating":6.309524},{"ISBN":3447,"rating":6.2729216},{"ISBN":6570,"rating":6.246822},{"ISBN":9322,"rating":6.244128}]}
{"userId":18994,"recommendations":[{"ISBN":9505,"rating":5.9880342},{"ISBN":7789,"rating":5.5379725},{"ISBN":9347,"rating":5.4408526},{"ISBN":9732,"rating":5.4370675},{"ISBN":9008,"rating":5.391768},{"ISBN":7009,"rating":5.318516},{"ISBN":7881,"rating":5.285494},{"ISBN":8561,"rating":5.2070136},{"ISBN":9624,"rating":5.1743503},{"ISBN":6712,"rating":5.149923}]}
{"userId":19217,"recommendations":[{"ISBN":9214,"rating":7.803396},{"ISBN":3502,"rating":6.584732},{"ISBN":8653,"rating":6.5709267},{"ISBN":1198,"rating":6.5435996},{"ISBN":9458,"rating":6.532475},{"ISBN":7844,"rating":6.410853},{"ISBN":8794,"rating":6.3978987},{"ISBN":5454,"rating":6.396567},{"ISBN":4594,"rating":6.351614},{"ISBN":4962,"rating":6.3332076}]}
{"userId":19349,"recommendations":[{"ISBN":9624,"rating":5.8562913},{"ISBN":5418,"rating":5.5941377},{"ISBN":9008,"rating":5.5450053},{"ISBN":9582,"rating":5.499723},{"ISBN":7844,"rating":5.440236},{"ISBN":9317,"rating":5.1508904},{"ISBN":9345,"rating":5.1467175},{"ISBN":6329,"rating":5.1256385},{"ISBN":4711,"rating":5.1065655},{"ISBN":5628,"rating":5.0183854}]}
{"userId":19492,"recommendations":[{"ISBN":9505,"rating":6.3999786},{"ISBN":9008,"rating":6.0604305},{"ISBN":7881,"rating":5.901363},{"ISBN":5919,"rating":5.6143646},{"ISBN":8014,"rating":5.539316},{"ISBN":6501,"rating":5.519127},{"ISBN":9441,"rating":5.515235},{"ISBN":7317,"rating":5.504199},{"ISBN":8013,"rating":5.492971},{"ISBN":4783,"rating":5.4643507}]}
{"userId":19528,"recommendations":[{"ISBN":6583,"rating":6.1884446},{"ISBN":9932,"rating":6.1567597},{"ISBN":5784,"rating":6.1154485},{"ISBN":7869,"rating":6.0305514},{"ISBN":8548,"rating":6.012271},{"ISBN":8854,"rating":5.8775005},{"ISBN":8200,"rating":5.8707824},{"ISBN":7754,"rating":5.8421125},{"ISBN":9815,"rating":5.841325},{"ISBN":3224,"rating":5.828478}]}
{"userId":19561,"recommendations":[{"ISBN":9214,"rating":5.136054},{"ISBN":9884,"rating":5.0323687},{"ISBN":9181,"rating":4.8363576},{"ISBN":8498,"rating":4.8205895},{"ISBN":8794,"rating":4.8136883},{"ISBN":5181,"rating":4.7328825},{"ISBN":6639,"rating":4.7225947},{"ISBN":5529,"rating":4.7174687},{"ISBN":5586,"rating":4.71379},{"ISBN":4507,"rating":4.6995783}]}
{"userId":20176,"recommendations":[{"ISBN":8601,"rating":6.9782243},{"ISBN":6605,"rating":6.051512},{"ISBN":3321,"rating":6.042419},{"ISBN":4873,"rating":6.021984},{"ISBN":6435,"rating":6.00283},{"ISBN":3581,"rating":5.939826},{"ISBN":1657,"rating":5.931266},{"ISBN":4220,"rating":5.9003325},{"ISBN":8548,"rating":5.874196},{"ISBN":5019,"rating":5.8679247}]}
{"userId":20406,"recommendations":[{"ISBN":7837,"rating":5.359356},{"ISBN":9011,"rating":5.122512},{"ISBN":9220,"rating":5.0432286},{"ISBN":9578,"rating":4.9583073},{"ISBN":3360,"rating":4.9331856},{"ISBN":8882,"rating":4.896499},{"ISBN":8946,"rating":4.88964},{"ISBN":5268,"rating":4.750935},{"ISBN":4955,"rating":4.737261},{"ISBN":8601,"rating":4.732992}]}
{"userId":20678,"recommendations":[{"ISBN":8907,"rating":5.2696695},{"ISBN":953,"rating":4.9174595},{"ISBN":8846,"rating":4.916885},{"ISBN":9714,"rating":4.913841},{"ISBN":7507,"rating":4.872589},{"ISBN":8259,"rating":4.8168507},{"ISBN":9320,"rating":4.7897935},{"ISBN":9208,"rating":4.6758194},{"ISBN":9997,"rating":4.615734},{"ISBN":9514,"rating":4.609981}]}
{"userId":20864,"recommendations":[{"ISBN":8601,"rating":7.2769327},{"ISBN":9505,"rating":7.072979},{"ISBN":8519,"rating":6.5827355},{"ISBN":9418,"rating":6.4493065},{"ISBN":7881,"rating":6.2543406},{"ISBN":8747,"rating":6.234947},{"ISBN":9978,"rating":6.18179},{"ISBN":7837,"rating":6.128809},{"ISBN":7337,"rating":6.122888},{"ISBN":7242,"rating":6.102919}]}
{"userId":21359,"recommendations":[{"ISBN":8601,"rating":5.0557775},{"ISBN":3628,"rating":4.790445},{"ISBN":8548,"rating":4.7868986},{"ISBN":7677,"rating":4.753172},{"ISBN":3491,"rating":4.742906},{"ISBN":7947,"rating":4.7373805},{"ISBN":1788,"rating":4.7311172},{"ISBN":9208,"rating":4.729921},{"ISBN":8946,"rating":4.728858},{"ISBN":6590,"rating":4.721233}]}
{"userId":21428,"recommendations":[{"ISBN":9220,"rating":7.5840445},{"ISBN":4154,"rating":7.5040083},{"ISBN":6160,"rating":7.2659197},{"ISBN":6120,"rating":7.1875315},{"ISBN":8882,"rating":7.0760508},{"ISBN":9516,"rating":7.0194435},{"ISBN":9568,"rating":6.913394},{"ISBN":8559,"rating":6.805156},{"ISBN":1338,"rating":6.7915525},{"ISBN":3360,"rating":6.6450324}]}
{"userId":21601,"recommendations":[{"ISBN":9008,"rating":6.364638},{"ISBN":8014,"rating":5.9992633},{"ISBN":7844,"rating":5.6655746},{"ISBN":6031,"rating":5.659933},{"ISBN":7455,"rating":5.5859737},{"ISBN":6920,"rating":5.5487647},{"ISBN":6401,"rating":5.543952},{"ISBN":3952,"rating":5.530818},{"ISBN":9624,"rating":5.4840465},{"ISBN":6590,"rating":5.470765}]}
{"userId":21809,"recommendations":[{"ISBN":7947,"rating":5.2718186},{"ISBN":7844,"rating":5.179831},{"ISBN":5208,"rating":5.1550074},{"ISBN":7039,"rating":5.130533},{"ISBN":6077,"rating":5.088139},{"ISBN":9732,"rating":5.0705876},{"ISBN":9566,"rating":5.055826},{"ISBN":4778,"rating":4.9752445},{"ISBN":8946,"rating":4.9657984},{"ISBN":3753,"rating":4.9375253}]}
{"userId":21919,"recommendations":[{"ISBN":9769,"rating":6.7836447},{"ISBN":7754,"rating":6.423996},{"ISBN":9322,"rating":6.1213994},{"ISBN":9505,"rating":6.0201325},{"ISBN":8519,"rating":5.9886823},{"ISBN":7444,"rating":5.895791},{"ISBN":9978,"rating":5.8437476},{"ISBN":9509,"rating":5.8385305},{"ISBN":7844,"rating":5.764942},{"ISBN":8170,"rating":5.7244916}]}
{"userId":22166,"recommendations":[{"ISBN":4962,"rating":7.0441265},{"ISBN":9008,"rating":6.6311765},{"ISBN":6570,"rating":6.237783},{"ISBN":9347,"rating":6.1315002},{"ISBN":5059,"rating":6.024876},{"ISBN":5623,"rating":5.9090424},{"ISBN":8992,"rating":5.8851013},{"ISBN":9119,"rating":5.8626685},{"ISBN":7736,"rating":5.8624144},{"ISBN":6769,"rating":5.811728}]}
{"userId":22399,"recommendations":[{"ISBN":9008,"rating":7.6558595},{"ISBN":6712,"rating":7.313294},{"ISBN":7881,"rating":6.8530927},{"ISBN":4783,"rating":6.657954},{"ISBN":8533,"rating":6.648728},{"ISBN":6570,"rating":6.646024},{"ISBN":6583,"rating":6.633715},{"ISBN":5454,"rating":6.627044},{"ISBN":9952,"rating":6.5404906},{"ISBN":8561,"rating":6.51847}]}
{"userId":22825,"recommendations":[{"ISBN":9732,"rating":5.590446},{"ISBN":9131,"rating":5.445681},{"ISBN":8636,"rating":5.3560133},{"ISBN":9206,"rating":5.1911626},{"ISBN":6810,"rating":5.163759},{"ISBN":5208,"rating":5.16348},{"ISBN":2845,"rating":5.1323605},{"ISBN":6076,"rating":5.1315722},{"ISBN":8566,"rating":5.065558},{"ISBN":8374,"rating":5.048464}]}
{"userId":22950,"recommendations":[{"ISBN":9932,"rating":5.0806527},{"ISBN":9008,"rating":5.059226},{"ISBN":9119,"rating":4.707103},{"ISBN":5005,"rating":4.705143},{"ISBN":9553,"rating":4.688887},{"ISBN":4344,"rating":4.678979},{"ISBN":9973,"rating":4.665559},{"ISBN":6947,"rating":4.6555405},{"ISBN":7405,"rating":4.644999},{"ISBN":6990,"rating":4.642451}]}
{"userId":23048,"recommendations":[{"ISBN":7754,"rating":5.7971034},{"ISBN":9553,"rating":5.3961096},{"ISBN":8548,"rating":5.379238},{"ISBN":8601,"rating":5.3713846},{"ISBN":6605,"rating":5.119617},{"ISBN":8220,"rating":5.047517},{"ISBN":9762,"rating":5.0328026},{"ISBN":8877,"rating":4.9923983},{"ISBN":9283,"rating":4.9868383},{"ISBN":9003,"rating":4.8935947}]}
{"userId":23072,"recommendations":[{"ISBN":9505,"rating":6.0583777},{"ISBN":9208,"rating":5.9612565},{"ISBN":7869,"rating":5.8487372},{"ISBN":5731,"rating":5.787249},{"ISBN":6583,"rating":5.7811418},{"ISBN":6962,"rating":5.717013},{"ISBN":608,"rating":5.701829},{"ISBN":8707,"rating":5.697888},{"ISBN":4940,"rating":5.688259},{"ISBN":6613,"rating":5.678488}]}
{"userId":23176,"recommendations":[{"ISBN":9505,"rating":6.9179068},{"ISBN":8519,"rating":6.706047},{"ISBN":9978,"rating":6.6281767},{"ISBN":8875,"rating":6.5739646},{"ISBN":7849,"rating":6.5212526},{"ISBN":9375,"rating":6.4837627},{"ISBN":7869,"rating":6.341582},{"ISBN":6583,"rating":6.336534},{"ISBN":9147,"rating":6.2843733},{"ISBN":9360,"rating":6.251636}]}
{"userId":23237,"recommendations":[{"ISBN":9001,"rating":7.5556173},{"ISBN":8573,"rating":6.918991},{"ISBN":8358,"rating":6.814292},{"ISBN":3669,"rating":6.6475844},{"ISBN":5130,"rating":6.5363226},{"ISBN":9672,"rating":6.4705706},{"ISBN":5778,"rating":6.4613304},{"ISBN":9010,"rating":6.3647494},{"ISBN":9843,"rating":6.300428},{"ISBN":9734,"rating":6.2719836}]}
{"userId":23584,"recommendations":[{"ISBN":6312,"rating":5.546579},{"ISBN":6096,"rating":5.532171},{"ISBN":9992,"rating":5.4292026},{"ISBN":8429,"rating":5.2717924},{"ISBN":9307,"rating":5.192768},{"ISBN":6543,"rating":5.1478686},{"ISBN":3637,"rating":5.0665083},{"ISBN":9374,"rating":5.0351253},{"ISBN":5542,"rating":4.9948177},{"ISBN":8157,"rating":4.9932985}]}
{"userId":23657,"recommendations":[{"ISBN":9769,"rating":7.3168592},{"ISBN":7754,"rating":6.889246},{"ISBN":5059,"rating":6.8298683},{"ISBN":3426,"rating":6.7395287},{"ISBN":8368,"rating":6.7386613},{"ISBN":8200,"rating":6.377279},{"ISBN":8421,"rating":6.270655},{"ISBN":8840,"rating":6.1594276},{"ISBN":9203,"rating":6.1207676},{"ISBN":8877,"rating":5.998985}]}
{"userId":23736,"recommendations":[{"ISBN":7844,"rating":6.1787314},{"ISBN":9932,"rating":5.929034},{"ISBN":9553,"rating":5.8987746},{"ISBN":9842,"rating":5.783295},{"ISBN":7401,"rating":5.7586336},{"ISBN":8548,"rating":5.735271},{"ISBN":4344,"rating":5.6864243},{"ISBN":9912,"rating":5.6614995},{"ISBN":9182,"rating":5.641134},{"ISBN":7754,"rating":5.6171856}]}
{"userId":23790,"recommendations":[{"ISBN":8056,"rating":6.074847},{"ISBN":3502,"rating":6.0289674},{"ISBN":9441,"rating":6.0052586},{"ISBN":6712,"rating":5.987915},{"ISBN":9932,"rating":5.9568224},{"ISBN":5435,"rating":5.871905},{"ISBN":9008,"rating":5.850723},{"ISBN":3447,"rating":5.8270893},{"ISBN":7129,"rating":5.822612},{"ISBN":6401,"rating":5.772973}]}
{"userId":24124,"recommendations":[{"ISBN":9932,"rating":5.822605},{"ISBN":9815,"rating":5.7702436},{"ISBN":8548,"rating":5.4069667},{"ISBN":9283,"rating":5.390726},{"ISBN":5784,"rating":5.378707},{"ISBN":9398,"rating":5.342505},{"ISBN":9492,"rating":5.325802},{"ISBN":3479,"rating":5.3207083},{"ISBN":8956,"rating":5.2969766},{"ISBN":4310,"rating":5.264122}]}
{"userId":24278,"recommendations":[{"ISBN":7736,"rating":6.512273},{"ISBN":7507,"rating":6.4973645},{"ISBN":6096,"rating":6.465471},{"ISBN":9677,"rating":6.365323},{"ISBN":9850,"rating":6.264064},{"ISBN":9008,"rating":6.205648},{"ISBN":5992,"rating":5.980422},{"ISBN":8369,"rating":5.9085903},{"ISBN":8639,"rating":5.78064},{"ISBN":5789,"rating":5.7208004}]}
{"userId":24441,"recommendations":[{"ISBN":6937,"rating":5.6143265},{"ISBN":6583,"rating":5.5571437},{"ISBN":8519,"rating":5.4684114},{"ISBN":7401,"rating":5.4667835},{"ISBN":6605,"rating":5.462064},{"ISBN":9247,"rating":5.4218063},{"ISBN":8875,"rating":5.4013777},{"ISBN":8548,"rating":5.397563},{"ISBN":9967,"rating":5.3899717},{"ISBN":8891,"rating":5.381588}]}
{"userId":24606,"recommendations":[{"ISBN":9220,"rating":6.2345805},{"ISBN":9850,"rating":6.0048437},{"ISBN":8183,"rating":5.799669},{"ISBN":5435,"rating":5.7110844},{"ISBN":9815,"rating":5.701298},{"ISBN":9568,"rating":5.6829762},{"ISBN":8239,"rating":5.6823893},{"ISBN":9516,"rating":5.646743},{"ISBN":9181,"rating":5.5855913},{"ISBN":8946,"rating":5.525887}]}
{"userId":24986,"recommendations":[{"ISBN":8382,"rating":6.7207813},{"ISBN":8601,"rating":6.478602},{"ISBN":9214,"rating":6.450745},{"ISBN":5059,"rating":6.296924},{"ISBN":9482,"rating":6.267706},{"ISBN":9246,"rating":6.1618705},{"ISBN":7715,"rating":6.0765605},{"ISBN":9768,"rating":6.02192},{"ISBN":7871,"rating":6.0114694},{"ISBN":7337,"rating":5.966509}]}
{"userId":25163,"recommendations":[{"ISBN":7871,"rating":7.6553636},{"ISBN":8601,"rating":7.402965},{"ISBN":8382,"rating":7.06872},{"ISBN":9220,"rating":6.6642466},{"ISBN":9002,"rating":6.597814},{"ISBN":7252,"rating":6.506559},{"ISBN":8616,"rating":6.4441595},{"ISBN":9284,"rating":6.330178},{"ISBN":3479,"rating":6.283188},{"ISBN":3821,"rating":6.2454424}]}
{"userId":25368,"recommendations":[{"ISBN":3502,"rating":4.9055805},{"ISBN":6920,"rating":4.777572},{"ISBN":7881,"rating":4.746986},{"ISBN":3491,"rating":4.7417717},{"ISBN":6590,"rating":4.7370157},{"ISBN":1788,"rating":4.7312465},{"ISBN":8807,"rating":4.7308416},{"ISBN":3628,"rating":4.727795},{"ISBN":5580,"rating":4.7230253},{"ISBN":8946,"rating":4.6987844}]}
{"userId":25467,"recommendations":[{"ISBN":5059,"rating":7.1394157},{"ISBN":9505,"rating":7.049857},{"ISBN":9347,"rating":6.720077},{"ISBN":8928,"rating":6.490845},{"ISBN":8519,"rating":6.4130664},{"ISBN":9831,"rating":6.35425},{"ISBN":7995,"rating":6.353281},{"ISBN":7369,"rating":6.3117433},{"ISBN":8606,"rating":6.2409554},{"ISBN":9262,"rating":6.1972394}]}
{"userId":25528,"recommendations":[{"ISBN":5059,"rating":5.0588994},{"ISBN":9505,"rating":4.984019},{"ISBN":9262,"rating":4.963085},{"ISBN":8601,"rating":4.8885508},{"ISBN":3669,"rating":4.8025894},{"ISBN":9119,"rating":4.764724},{"ISBN":8747,"rating":4.692516},{"ISBN":4462,"rating":4.6801515},{"ISBN":8548,"rating":4.6783657},{"ISBN":8519,"rating":4.652471}]}
{"userId":25766,"recommendations":[{"ISBN":4154,"rating":10.215395},{"ISBN":1338,"rating":9.357199},{"ISBN":7369,"rating":7.6621437},{"ISBN":8276,"rating":7.5852947},{"ISBN":6989,"rating":7.301496},{"ISBN":5971,"rating":7.2207212},{"ISBN":9824,"rating":7.0885334},{"ISBN":9705,"rating":7.070676},{"ISBN":9076,"rating":7.0602703},{"ISBN":9534,"rating":6.9576817}]}
{"userId":25869,"recommendations":[{"ISBN":4154,"rating":8.45177},{"ISBN":1338,"rating":8.424496},{"ISBN":5653,"rating":7.4635787},{"ISBN":9732,"rating":7.4525304},{"ISBN":6543,"rating":7.233495},{"ISBN":8374,"rating":7.193961},{"ISBN":5208,"rating":7.087839},{"ISBN":7756,"rating":7.0250163},{"ISBN":8559,"rating":6.7498918},{"ISBN":8636,"rating":6.740139}]}
{"userId":26109,"recommendations":[{"ISBN":9505,"rating":5.0521364},{"ISBN":9328,"rating":4.2857146},{"ISBN":4274,"rating":4.27577},{"ISBN":6543,"rating":4.2158895},{"ISBN":9732,"rating":4.091127},{"ISBN":7597,"rating":4.0606685},{"ISBN":4835,"rating":4.034595},{"ISBN":7844,"rating":4.0259132},{"ISBN":464,"rating":3.9848232},{"ISBN":2236,"rating":3.9804566}]}
{"userId":26738,"recommendations":[{"ISBN":7881,"rating":6.7924647},{"ISBN":9345,"rating":6.729182},{"ISBN":5454,"rating":6.24135},{"ISBN":6329,"rating":6.148643},{"ISBN":4783,"rating":6.1178007},{"ISBN":9441,"rating":6.022193},{"ISBN":9624,"rating":5.976419},{"ISBN":9008,"rating":5.8403373},{"ISBN":3502,"rating":5.780933},{"ISBN":4711,"rating":5.7458253}]}
{"userId":26816,"recommendations":[{"ISBN":9732,"rating":5.3567467},{"ISBN":7756,"rating":5.1065264},{"ISBN":9008,"rating":5.1007857},{"ISBN":9624,"rating":4.9109235},{"ISBN":9439,"rating":4.8841753},{"ISBN":7515,"rating":4.8124385},{"ISBN":7401,"rating":4.8114214},{"ISBN":6312,"rating":4.7984796},{"ISBN":8374,"rating":4.776442},{"ISBN":7844,"rating":4.7666726}]}
{"userId":26883,"recommendations":[{"ISBN":8946,"rating":4.928393},{"ISBN":9479,"rating":4.906551},{"ISBN":8548,"rating":4.879476},{"ISBN":9158,"rating":4.873796},{"ISBN":5189,"rating":4.8164554},{"ISBN":8636,"rating":4.7517576},{"ISBN":6772,"rating":4.7398834},{"ISBN":4898,"rating":4.725073},{"ISBN":9553,"rating":4.6940618},{"ISBN":9884,"rating":4.650651}]}
{"userId":26959,"recommendations":[{"ISBN":8601,"rating":6.263259},{"ISBN":7881,"rating":6.1033754},{"ISBN":9345,"rating":5.973955},{"ISBN":9260,"rating":5.41062},{"ISBN":4780,"rating":5.406897},{"ISBN":9578,"rating":5.3175054},{"ISBN":7039,"rating":5.2506866},{"ISBN":4785,"rating":5.2442255},{"ISBN":5872,"rating":5.2390566},{"ISBN":4755,"rating":5.227836}]}
{"userId":27075,"recommendations":[{"ISBN":9220,"rating":7.574318},{"ISBN":5102,"rating":7.399744},{"ISBN":9193,"rating":6.835849},{"ISBN":8183,"rating":6.5953364},{"ISBN":9292,"rating":6.5086513},{"ISBN":8217,"rating":6.417394},{"ISBN":9238,"rating":6.359914},{"ISBN":7871,"rating":6.3491063},{"ISBN":4898,"rating":6.2535853},{"ISBN":4809,"rating":6.239201}]}
{"userId":27086,"recommendations":[{"ISBN":8948,"rating":7.1829963},{"ISBN":7754,"rating":7.1569815},{"ISBN":3821,"rating":6.808168},{"ISBN":8875,"rating":6.791507},{"ISBN":9214,"rating":6.7764535},{"ISBN":7715,"rating":6.6831646},{"ISBN":7457,"rating":6.6092396},{"ISBN":9679,"rating":6.593582},{"ISBN":5589,"rating":6.561838},{"ISBN":3719,"rating":6.5440173}]}
{"userId":27320,"recommendations":[{"ISBN":1935,"rating":7.3677053},{"ISBN":4154,"rating":6.352407},{"ISBN":9732,"rating":6.188643},{"ISBN":1338,"rating":6.1644545},{"ISBN":2236,"rating":5.994571},{"ISBN":464,"rating":5.841035},{"ISBN":7873,"rating":5.7867165},{"ISBN":7369,"rating":5.7550793},{"ISBN":9824,"rating":5.7460275},{"ISBN":5012,"rating":5.744865}]}
{"userId":27575,"recommendations":[{"ISBN":8948,"rating":7.1623154},{"ISBN":8946,"rating":6.263843},{"ISBN":8580,"rating":6.2339306},{"ISBN":9357,"rating":6.229497},{"ISBN":7457,"rating":6.152209},{"ISBN":5730,"rating":6.1380734},{"ISBN":7485,"rating":6.1226983},{"ISBN":8636,"rating":6.072319},{"ISBN":6825,"rating":5.9865394},{"ISBN":2100,"rating":5.978317}]}
{"userId":27586,"recommendations":[{"ISBN":9214,"rating":8.953525},{"ISBN":9335,"rating":7.6310067},{"ISBN":8948,"rating":7.2991543},{"ISBN":4991,"rating":7.2985125},{"ISBN":6216,"rating":7.181115},{"ISBN":9677,"rating":7.1171246},{"ISBN":4962,"rating":7.021447},{"ISBN":8653,"rating":6.9052267},{"ISBN":3637,"rating":6.9043827},{"ISBN":9017,"rating":6.8943386}]}
{"userId":27925,"recommendations":[{"ISBN":7401,"rating":4.9547606},{"ISBN":9534,"rating":4.869004},{"ISBN":8403,"rating":4.86099},{"ISBN":9884,"rating":4.791823},{"ISBN":5730,"rating":4.7717853},{"ISBN":9842,"rating":4.767568},{"ISBN":6032,"rating":4.751403},{"ISBN":7844,"rating":4.721572},{"ISBN":6603,"rating":4.700712},{"ISBN":7988,"rating":4.698826}]}
{"userId":27926,"recommendations":[{"ISBN":9260,"rating":6.3309364},{"ISBN":9379,"rating":6.251853},{"ISBN":4154,"rating":6.1603937},{"ISBN":9505,"rating":6.0475793},{"ISBN":8882,"rating":6.0399103},{"ISBN":7130,"rating":5.982608},{"ISBN":9709,"rating":5.9664273},{"ISBN":9006,"rating":5.920195},{"ISBN":6893,"rating":5.914095},{"ISBN":7480,"rating":5.868951}]}
{"userId":28196,"recommendations":[{"ISBN":6450,"rating":7.399491},{"ISBN":8754,"rating":7.065349},{"ISBN":6948,"rating":6.905848},{"ISBN":9505,"rating":6.8042784},{"ISBN":9808,"rating":6.666558},{"ISBN":9322,"rating":6.6584373},{"ISBN":9988,"rating":6.6256356},{"ISBN":7995,"rating":6.5629764},{"ISBN":9436,"rating":6.5515847},{"ISBN":8013,"rating":6.5220413}]}
{"userId":28303,"recommendations":[{"ISBN":9534,"rating":6.4115887},{"ISBN":4154,"rating":6.158948},{"ISBN":1338,"rating":5.7666373},{"ISBN":9769,"rating":5.665382},{"ISBN":9076,"rating":5.5307493},{"ISBN":4868,"rating":5.5284524},{"ISBN":6543,"rating":5.4536357},{"ISBN":9182,"rating":5.4297757},{"ISBN":7869,"rating":5.3977947},{"ISBN":9329,"rating":5.3494077}]}
{"userId":28401,"recommendations":[{"ISBN":9347,"rating":5.98697},{"ISBN":5454,"rating":5.948393},{"ISBN":7129,"rating":5.8565807},{"ISBN":9441,"rating":5.7899833},{"ISBN":8616,"rating":5.750811},{"ISBN":3224,"rating":5.6768885},{"ISBN":9505,"rating":5.612698},{"ISBN":6712,"rating":5.609501},{"ISBN":5922,"rating":5.558503},{"ISBN":3502,"rating":5.5493846}]}
{"userId":28403,"recommendations":[{"ISBN":8522,"rating":8.498329},{"ISBN":9884,"rating":7.4948473},{"ISBN":5653,"rating":7.268569},{"ISBN":9962,"rating":7.2005634},{"ISBN":9355,"rating":7.0169544},{"ISBN":8271,"rating":7.00107},{"ISBN":9374,"rating":6.9413943},{"ISBN":3981,"rating":6.9363074},{"ISBN":5219,"rating":6.912822},{"ISBN":8372,"rating":6.806521}]}
{"userId":28405,"recommendations":[{"ISBN":9884,"rating":4.7023263},{"ISBN":9123,"rating":4.625254},{"ISBN":9324,"rating":4.56206},{"ISBN":9553,"rating":4.5230093},{"ISBN":8014,"rating":4.504657},{"ISBN":9531,"rating":4.488184},{"ISBN":8926,"rating":4.476112},{"ISBN":4969,"rating":4.4740176},{"ISBN":9551,"rating":4.4729996},{"ISBN":8548,"rating":4.438925}]}
{"userId":28444,"recommendations":[{"ISBN":7871,"rating":6.4174466},{"ISBN":9850,"rating":6.3096724},{"ISBN":3224,"rating":5.778504},{"ISBN":6712,"rating":5.7084217},{"ISBN":2928,"rating":5.684157},{"ISBN":9002,"rating":5.6680455},{"ISBN":8183,"rating":5.629447},{"ISBN":2272,"rating":5.601751},{"ISBN":6089,"rating":5.591611},{"ISBN":7507,"rating":5.5830307}]}
{"userId":28446,"recommendations":[{"ISBN":7881,"rating":6.7131553},{"ISBN":5454,"rating":6.357027},{"ISBN":9214,"rating":6.311427},{"ISBN":3502,"rating":6.2938375},{"ISBN":9714,"rating":6.2287555},{"ISBN":8601,"rating":6.2234297},{"ISBN":6798,"rating":6.082999},{"ISBN":8259,"rating":6.0339484},{"ISBN":8498,"rating":6.0172954},{"ISBN":7110,"rating":5.935167}]}
{"userId":28586,"recommendations":[{"ISBN":1338,"rating":6.370841},{"ISBN":4154,"rating":6.201958},{"ISBN":464,"rating":6.093359},{"ISBN":2236,"rating":6.027422},{"ISBN":5208,"rating":5.998309},{"ISBN":4809,"rating":5.9721375},{"ISBN":9076,"rating":5.952895},{"ISBN":9134,"rating":5.918537},{"ISBN":6102,"rating":5.8593335},{"ISBN":9399,"rating":5.811231}]}
{"userId":28668,"recommendations":[{"ISBN":9932,"rating":5.8341327},{"ISBN":6120,"rating":5.5316453},{"ISBN":9815,"rating":5.4637156},{"ISBN":8946,"rating":5.4317966},{"ISBN":9399,"rating":5.3760986},{"ISBN":8326,"rating":5.374383},{"ISBN":5784,"rating":5.363432},{"ISBN":8056,"rating":5.361536},{"ISBN":8223,"rating":5.278373},{"ISBN":4898,"rating":5.245455}]}
{"userId":29345,"recommendations":[{"ISBN":9505,"rating":6.374123},{"ISBN":2236,"rating":5.9283724},{"ISBN":464,"rating":5.84936},{"ISBN":6102,"rating":5.6046085},{"ISBN":9076,"rating":5.548992},{"ISBN":4154,"rating":5.543776},{"ISBN":1338,"rating":5.537327},{"ISBN":4778,"rating":5.536204},{"ISBN":7844,"rating":5.535668},{"ISBN":7404,"rating":5.4764495}]}
{"userId":30124,"recommendations":[{"ISBN":6712,"rating":6.033639},{"ISBN":9441,"rating":5.743247},{"ISBN":3502,"rating":5.6225524},{"ISBN":6613,"rating":5.588848},{"ISBN":4783,"rating":5.558913},{"ISBN":5038,"rating":5.5232444},{"ISBN":8561,"rating":5.505389},{"ISBN":8592,"rating":5.4524403},{"ISBN":6093,"rating":5.398574},{"ISBN":4766,"rating":5.3748155}]}
{"userId":30307,"recommendations":[{"ISBN":8014,"rating":5.2301908},{"ISBN":9119,"rating":5.1410804},{"ISBN":6971,"rating":5.1378937},{"ISBN":8403,"rating":5.038352},{"ISBN":9551,"rating":4.99114},{"ISBN":5005,"rating":4.9903016},{"ISBN":5524,"rating":4.952034},{"ISBN":9208,"rating":4.9507036},{"ISBN":3628,"rating":4.9237757},{"ISBN":7401,"rating":4.916374}]}
{"userId":30429,"recommendations":[{"ISBN":9011,"rating":6.317665},{"ISBN":9505,"rating":6.304372},{"ISBN":7837,"rating":6.01252},{"ISBN":5454,"rating":5.9729795},{"ISBN":7881,"rating":5.9369955},{"ISBN":6784,"rating":5.8144636},{"ISBN":9402,"rating":5.8117213},{"ISBN":4783,"rating":5.8082886},{"ISBN":9441,"rating":5.775755},{"ISBN":9709,"rating":5.771267}]}
{"userId":30682,"recommendations":[{"ISBN":8875,"rating":6.125016},{"ISBN":8948,"rating":5.861012},{"ISBN":9790,"rating":5.575937},{"ISBN":9978,"rating":5.4193125},{"ISBN":7715,"rating":5.340693},{"ISBN":9505,"rating":5.333113},{"ISBN":5325,"rating":5.2952375},{"ISBN":8580,"rating":5.2869277},{"ISBN":7837,"rating":5.279028},{"ISBN":8336,"rating":5.27636}]}
{"userId":31058,"recommendations":[{"ISBN":7844,"rating":5.985373},{"ISBN":8479,"rating":5.783745},{"ISBN":8548,"rating":5.56721},{"ISBN":7988,"rating":5.456823},{"ISBN":9260,"rating":5.438714},{"ISBN":7457,"rating":5.4121127},{"ISBN":7947,"rating":5.364316},{"ISBN":8358,"rating":5.3588133},{"ISBN":8601,"rating":5.3448267},{"ISBN":9158,"rating":5.3389087}]}
{"userId":31099,"recommendations":[{"ISBN":4154,"rating":7.58107},{"ISBN":8882,"rating":7.5808797},{"ISBN":8948,"rating":7.1929607},{"ISBN":9260,"rating":6.6636343},{"ISBN":4955,"rating":6.5980616},{"ISBN":6160,"rating":6.542816},{"ISBN":8559,"rating":6.5396533},{"ISBN":5695,"rating":6.482893},{"ISBN":3360,"rating":6.321472},{"ISBN":7226,"rating":6.312152}]}
{"userId":31497,"recommendations":[{"ISBN":8429,"rating":6.448076},{"ISBN":953,"rating":6.1310368},{"ISBN":5731,"rating":6.0845475},{"ISBN":7849,"rating":6.0634575},{"ISBN":8561,"rating":5.9337816},{"ISBN":4766,"rating":5.89518},{"ISBN":9732,"rating":5.881202},{"ISBN":6618,"rating":5.8737655},{"ISBN":9265,"rating":5.863944},{"ISBN":936,"rating":5.8556156}]}
{"userId":31518,"recommendations":[{"ISBN":8601,"rating":5.633222},{"ISBN":8948,"rating":5.5077095},{"ISBN":8479,"rating":5.2965913},{"ISBN":7039,"rating":5.279292},{"ISBN":9260,"rating":5.197954},{"ISBN":8946,"rating":5.1938376},{"ISBN":7457,"rating":5.1744814},{"ISBN":9345,"rating":5.122963},{"ISBN":7440,"rating":5.0843077},{"ISBN":7844,"rating":5.0528374}]}
{"userId":32212,"recommendations":[{"ISBN":3502,"rating":6.288134},{"ISBN":9214,"rating":6.02974},{"ISBN":8794,"rating":5.9742055},{"ISBN":7129,"rating":5.7849503},{"ISBN":8663,"rating":5.783878},{"ISBN":7670,"rating":5.70766},{"ISBN":6720,"rating":5.6886916},{"ISBN":6639,"rating":5.684193},{"ISBN":5038,"rating":5.68141},{"ISBN":8807,"rating":5.678781}]}
{"userId":32249,"recommendations":[{"ISBN":9214,"rating":5.294096},{"ISBN":7844,"rating":5.183863},{"ISBN":7947,"rating":5.1644444},{"ISBN":8479,"rating":5.08982},{"ISBN":6077,"rating":5.080147},{"ISBN":4594,"rating":5.077939},{"ISBN":9798,"rating":5.0764136},{"ISBN":8948,"rating":5.070869},{"ISBN":9732,"rating":5.0588613},{"ISBN":1026,"rating":5.034871}]}
{"userId":32432,"recommendations":[{"ISBN":5845,"rating":4.972624},{"ISBN":6032,"rating":4.9109545},{"ISBN":6583,"rating":4.9022536},{"ISBN":6089,"rating":4.714946},{"ISBN":7736,"rating":4.682628},{"ISBN":7695,"rating":4.674203},{"ISBN":9008,"rating":4.6685576},{"ISBN":8854,"rating":4.642055},{"ISBN":9003,"rating":4.624954},{"ISBN":8639,"rating":4.5725594}]}
{"userId":33081,"recommendations":[{"ISBN":9932,"rating":7.471314},{"ISBN":8326,"rating":6.99501},{"ISBN":9008,"rating":6.8729286},{"ISBN":6522,"rating":6.720182},{"ISBN":8639,"rating":6.718407},{"ISBN":9992,"rating":6.6512194},{"ISBN":9529,"rating":6.6419454},{"ISBN":8505,"rating":6.621391},{"ISBN":5653,"rating":6.562621},{"ISBN":6606,"rating":6.5462785}]}
{"userId":33392,"recommendations":[{"ISBN":6583,"rating":6.6399317},{"ISBN":8854,"rating":6.601344},{"ISBN":9322,"rating":6.3778872},{"ISBN":9008,"rating":6.3405747},{"ISBN":3224,"rating":6.282069},{"ISBN":6712,"rating":6.257024},{"ISBN":9505,"rating":6.1262426},{"ISBN":9686,"rating":6.102509},{"ISBN":9932,"rating":6.058468},{"ISBN":9737,"rating":6.039869}]}
{"userId":33522,"recommendations":[{"ISBN":9220,"rating":6.65411},{"ISBN":5953,"rating":5.903773},{"ISBN":7871,"rating":5.82481},{"ISBN":255,"rating":5.8049884},{"ISBN":3502,"rating":5.7850986},{"ISBN":9002,"rating":5.715045},{"ISBN":6712,"rating":5.6272755},{"ISBN":6592,"rating":5.6181912},{"ISBN":6613,"rating":5.60103},{"ISBN":9922,"rating":5.584568}]}
{"userId":33939,"recommendations":[{"ISBN":7844,"rating":5.890556},{"ISBN":3753,"rating":5.501549},{"ISBN":422,"rating":5.4749875},{"ISBN":9008,"rating":5.4630146},{"ISBN":9569,"rating":5.4165626},{"ISBN":7947,"rating":5.412961},{"ISBN":6920,"rating":5.4069514},{"ISBN":25,"rating":5.392683},{"ISBN":2101,"rating":5.385968},{"ISBN":8548,"rating":5.3787093}]}
{"userId":33983,"recommendations":[{"ISBN":7104,"rating":7.491214},{"ISBN":3479,"rating":7.2549024},{"ISBN":7715,"rating":7.24788},{"ISBN":8875,"rating":7.2390466},{"ISBN":9220,"rating":7.129661},{"ISBN":8368,"rating":7.114521},{"ISBN":7869,"rating":6.999171},{"ISBN":7242,"rating":6.93006},{"ISBN":8601,"rating":6.9264007},{"ISBN":7871,"rating":6.898567}]}
{"userId":34149,"recommendations":[{"ISBN":9158,"rating":6.2839074},{"ISBN":9322,"rating":6.232651},{"ISBN":7754,"rating":6.229251},{"ISBN":9193,"rating":5.903372},{"ISBN":8956,"rating":5.800518},{"ISBN":5102,"rating":5.7157316},{"ISBN":9479,"rating":5.7151146},{"ISBN":8183,"rating":5.6232605},{"ISBN":9884,"rating":5.592707},{"ISBN":8314,"rating":5.544648}]}
{"userId":34410,"recommendations":[{"ISBN":8063,"rating":6.9786496},{"ISBN":5845,"rating":6.9570937},{"ISBN":8170,"rating":6.7335863},{"ISBN":7444,"rating":6.6661377},{"ISBN":8338,"rating":6.657355},{"ISBN":9322,"rating":6.575624},{"ISBN":7401,"rating":6.5754075},{"ISBN":8519,"rating":6.5415745},{"ISBN":9219,"rating":6.53755},{"ISBN":8027,"rating":6.5292635}]}
{"userId":34462,"recommendations":[{"ISBN":7844,"rating":6.089629},{"ISBN":9624,"rating":6.010201},{"ISBN":9008,"rating":5.914685},{"ISBN":8999,"rating":5.8798614},{"ISBN":7039,"rating":5.8766923},{"ISBN":9884,"rating":5.8564906},{"ISBN":7455,"rating":5.7878156},{"ISBN":9582,"rating":5.780509},{"ISBN":7140,"rating":5.7704797},{"ISBN":1198,"rating":5.7584424}]}
{"userId":35160,"recommendations":[{"ISBN":9534,"rating":5.672093},{"ISBN":9505,"rating":5.529907},{"ISBN":9824,"rating":5.283716},{"ISBN":4154,"rating":5.241111},{"ISBN":7369,"rating":5.214195},{"ISBN":7869,"rating":5.165449},{"ISBN":9897,"rating":5.148951},{"ISBN":4346,"rating":5.094545},{"ISBN":9734,"rating":5.0565453},{"ISBN":2236,"rating":5.0404925}]}
{"userId":35413,"recommendations":[{"ISBN":8170,"rating":8.404188},{"ISBN":8314,"rating":8.204646},{"ISBN":9322,"rating":7.6270976},{"ISBN":9831,"rating":7.4160566},{"ISBN":5845,"rating":7.4111643},{"ISBN":7401,"rating":7.3155427},{"ISBN":9219,"rating":7.2791796},{"ISBN":8519,"rating":7.235015},{"ISBN":8063,"rating":7.17896},{"ISBN":7444,"rating":7.147915}]}
{"userId":35421,"recommendations":[{"ISBN":9534,"rating":5.4983},{"ISBN":6032,"rating":5.4518657},{"ISBN":9032,"rating":5.3366275},{"ISBN":7736,"rating":5.282829},{"ISBN":6419,"rating":5.145347},{"ISBN":9850,"rating":5.1007953},{"ISBN":9516,"rating":5.0922604},{"ISBN":6965,"rating":5.0463552},{"ISBN":7482,"rating":4.96392},{"ISBN":6400,"rating":4.924558}]}
{"userId":35644,"recommendations":[{"ISBN":9516,"rating":6.704313},{"ISBN":1935,"rating":6.6573114},{"ISBN":9392,"rating":6.404197},{"ISBN":9815,"rating":6.2921906},{"ISBN":9110,"rating":6.27074},{"ISBN":9123,"rating":6.07917},{"ISBN":3628,"rating":6.0153503},{"ISBN":9208,"rating":5.995289},{"ISBN":9566,"rating":5.9296255},{"ISBN":5563,"rating":5.9202814}]}
{"userId":35744,"recommendations":[{"ISBN":5059,"rating":5.5647607},{"ISBN":9347,"rating":5.3030286},{"ISBN":6570,"rating":5.173874},{"ISBN":8854,"rating":4.9939613},{"ISBN":9505,"rating":4.986674},{"ISBN":9322,"rating":4.9336653},{"ISBN":9686,"rating":4.9208484},{"ISBN":9932,"rating":4.835034},{"ISBN":8928,"rating":4.734598},{"ISBN":5142,"rating":4.734077}]}
{"userId":35781,"recommendations":[{"ISBN":8559,"rating":5.427384},{"ISBN":8636,"rating":5.29714},{"ISBN":9356,"rating":5.2786813},{"ISBN":4154,"rating":5.261862},{"ISBN":8239,"rating":5.1825447},{"ISBN":8948,"rating":5.0783377},{"ISBN":1338,"rating":5.0322943},{"ISBN":5208,"rating":5.0146813},{"ISBN":6543,"rating":4.960657},{"ISBN":9798,"rating":4.9418707}]}
{"userId":35892,"recommendations":[{"ISBN":5059,"rating":6.0494094},{"ISBN":4518,"rating":5.973938},{"ISBN":9347,"rating":5.9737816},{"ISBN":7844,"rating":5.8018785},{"ISBN":9505,"rating":5.7988667},{"ISBN":9686,"rating":5.7549033},{"ISBN":9734,"rating":5.726912},{"ISBN":8854,"rating":5.7232904},{"ISBN":9071,"rating":5.7084737},{"ISBN":9294,"rating":5.7046027}]}
{"userId":35987,"recommendations":[{"ISBN":6158,"rating":5.797892},{"ISBN":8854,"rating":5.437695},{"ISBN":9008,"rating":5.4051485},{"ISBN":7369,"rating":5.369288},{"ISBN":6522,"rating":5.321737},{"ISBN":9347,"rating":5.2779026},{"ISBN":8522,"rating":5.2709455},{"ISBN":8634,"rating":5.2383776},{"ISBN":9492,"rating":5.226993},{"ISBN":9932,"rating":5.221641}]}
{"userId":36141,"recommendations":[{"ISBN":7337,"rating":6.499307},{"ISBN":9505,"rating":6.449385},{"ISBN":9418,"rating":6.340342},{"ISBN":8601,"rating":6.3068027},{"ISBN":8519,"rating":6.267788},{"ISBN":7876,"rating":6.1926327},{"ISBN":8747,"rating":6.1575847},{"ISBN":5059,"rating":6.094881},{"ISBN":8014,"rating":5.6922345},{"ISBN":1777,"rating":5.689221}]}
{"userId":36760,"recommendations":[{"ISBN":9732,"rating":7.013863},{"ISBN":9982,"rating":6.510999},{"ISBN":7581,"rating":6.404168},{"ISBN":9008,"rating":6.392667},{"ISBN":7193,"rating":6.340242},{"ISBN":9714,"rating":6.168268},{"ISBN":5012,"rating":6.070347},{"ISBN":4845,"rating":6.044154},{"ISBN":7369,"rating":5.9741993},{"ISBN":5828,"rating":5.944276}]}
{"userId":37042,"recommendations":[{"ISBN":7881,"rating":5.894182},{"ISBN":6583,"rating":5.657329},{"ISBN":9997,"rating":5.4089265},{"ISBN":9714,"rating":5.3698773},{"ISBN":4755,"rating":5.327122},{"ISBN":8907,"rating":5.290858},{"ISBN":8580,"rating":5.25449},{"ISBN":9578,"rating":5.188193},{"ISBN":9004,"rating":5.183777},{"ISBN":9008,"rating":5.159771}]}
{"userId":37062,"recommendations":[{"ISBN":9220,"rating":6.1855435},{"ISBN":9379,"rating":6.105895},{"ISBN":9260,"rating":6.1002045},{"ISBN":9505,"rating":6.0951986},{"ISBN":7950,"rating":5.8813186},{"ISBN":9768,"rating":5.812383},{"ISBN":3479,"rating":5.7889204},{"ISBN":9482,"rating":5.6779566},{"ISBN":9071,"rating":5.64688},{"ISBN":7165,"rating":5.638533}]}
{"userId":37084,"recommendations":[{"ISBN":1935,"rating":5.9090576},{"ISBN":9534,"rating":5.8224835},{"ISBN":9123,"rating":5.8133006},{"ISBN":9815,"rating":5.808884},{"ISBN":6971,"rating":5.7227693},{"ISBN":9551,"rating":5.7100983},{"ISBN":8611,"rating":5.670671},{"ISBN":9032,"rating":5.6407},{"ISBN":9392,"rating":5.6301155},{"ISBN":9208,"rating":5.5786877}]}
{"userId":37105,"recommendations":[{"ISBN":9714,"rating":6.7051907},{"ISBN":9732,"rating":6.5684714},{"ISBN":7900,"rating":6.5209184},{"ISBN":9997,"rating":6.4329524},{"ISBN":6031,"rating":6.281706},{"ISBN":7039,"rating":6.254146},{"ISBN":7147,"rating":6.1748185},{"ISBN":5418,"rating":6.1422253},{"ISBN":9837,"rating":6.1165853},{"ISBN":3104,"rating":6.108968}]}
{"userId":37358,"recommendations":[{"ISBN":7844,"rating":6.261977},{"ISBN":9345,"rating":5.961421},{"ISBN":9553,"rating":5.676242},{"ISBN":7537,"rating":5.663294},{"ISBN":9912,"rating":5.6538787},{"ISBN":7039,"rating":5.6195035},{"ISBN":9624,"rating":5.5312934},{"ISBN":9891,"rating":5.514331},{"ISBN":9243,"rating":5.4174542},{"ISBN":7147,"rating":5.415266}]}
{"userId":37553,"recommendations":[{"ISBN":9732,"rating":5.9716835},{"ISBN":5418,"rating":5.4498525},{"ISBN":2236,"rating":5.4293528},{"ISBN":9219,"rating":5.3067417},{"ISBN":8120,"rating":5.1608877},{"ISBN":9824,"rating":5.1467376},{"ISBN":9505,"rating":5.12035},{"ISBN":464,"rating":5.1024747},{"ISBN":7844,"rating":5.0837545},{"ISBN":7483,"rating":4.977292}]}
{"userId":37695,"recommendations":[{"ISBN":9992,"rating":7.7355075},{"ISBN":6543,"rating":7.163947},{"ISBN":9962,"rating":7.0023994},{"ISBN":8559,"rating":6.7262673},{"ISBN":9637,"rating":6.3291097},{"ISBN":5653,"rating":6.212479},{"ISBN":7798,"rating":6.1619754},{"ISBN":6312,"rating":6.1391726},{"ISBN":5554,"rating":6.114351},{"ISBN":5731,"rating":6.0421324}]}
{"userId":38012,"recommendations":[{"ISBN":9505,"rating":5.7316284},{"ISBN":6543,"rating":5.3096476},{"ISBN":7947,"rating":5.119268},{"ISBN":7480,"rating":5.104112},{"ISBN":9732,"rating":5.036219},{"ISBN":2236,"rating":4.9458666},{"ISBN":9208,"rating":4.907929},{"ISBN":9162,"rating":4.902542},{"ISBN":8580,"rating":4.894284},{"ISBN":5731,"rating":4.8868575}]}
{"userId":38664,"recommendations":[{"ISBN":9932,"rating":5.519859},{"ISBN":8639,"rating":5.334673},{"ISBN":5653,"rating":5.1652207},{"ISBN":4663,"rating":5.120783},{"ISBN":9008,"rating":5.119645},{"ISBN":8429,"rating":5.056068},{"ISBN":9374,"rating":5.0284505},{"ISBN":5784,"rating":4.9880495},{"ISBN":6312,"rating":4.9785542},{"ISBN":9529,"rating":4.968629}]}
{"userId":38701,"recommendations":[{"ISBN":9815,"rating":5.231673},{"ISBN":9534,"rating":4.995822},{"ISBN":8548,"rating":4.9935827},{"ISBN":9932,"rating":4.8326454},{"ISBN":9032,"rating":4.788871},{"ISBN":5784,"rating":4.7843323},{"ISBN":8946,"rating":4.7823143},{"ISBN":9842,"rating":4.7602043},{"ISBN":3628,"rating":4.697092},{"ISBN":8415,"rating":4.663952}]}
{"userId":38751,"recommendations":[{"ISBN":9850,"rating":5.2905536},{"ISBN":6096,"rating":5.100461},{"ISBN":8875,"rating":4.9515247},{"ISBN":9374,"rating":4.899255},{"ISBN":9815,"rating":4.892434},{"ISBN":6400,"rating":4.86871},{"ISBN":4451,"rating":4.8585696},{"ISBN":6642,"rating":4.8494644},{"ISBN":7942,"rating":4.8419604},{"ISBN":8663,"rating":4.841366}]}
{"userId":38875,"recommendations":[{"ISBN":9345,"rating":7.1397195},{"ISBN":7844,"rating":6.576249},{"ISBN":9479,"rating":6.4897804},{"ISBN":7754,"rating":6.3529058},{"ISBN":9553,"rating":6.268933},{"ISBN":8636,"rating":6.1956673},{"ISBN":7592,"rating":6.17508},{"ISBN":9158,"rating":6.0747375},{"ISBN":9322,"rating":6.030237},{"ISBN":8580,"rating":6.0042872}]}
{"userId":39393,"recommendations":[{"ISBN":7881,"rating":5.899314},{"ISBN":9008,"rating":5.771859},{"ISBN":9505,"rating":5.557007},{"ISBN":7317,"rating":5.5358076},{"ISBN":9881,"rating":5.530131},{"ISBN":9055,"rating":5.461319},{"ISBN":5244,"rating":5.4048114},{"ISBN":6712,"rating":5.3571997},{"ISBN":6395,"rating":5.3402014},{"ISBN":6583,"rating":5.327768}]}
{"userId":39558,"recommendations":[{"ISBN":7754,"rating":6.986154},{"ISBN":8956,"rating":6.5296645},{"ISBN":9534,"rating":6.4068394},{"ISBN":8548,"rating":6.328603},{"ISBN":9283,"rating":6.2652664},{"ISBN":5059,"rating":6.258318},{"ISBN":8877,"rating":6.2036433},{"ISBN":9631,"rating":6.029295},{"ISBN":9815,"rating":6.0192795},{"ISBN":9072,"rating":6.0074906}]}
{"userId":39566,"recommendations":[{"ISBN":7736,"rating":6.499476},{"ISBN":6032,"rating":6.425273},{"ISBN":4962,"rating":6.3150363},{"ISBN":8259,"rating":6.150179},{"ISBN":7507,"rating":6.0803227},{"ISBN":9792,"rating":5.9544854},{"ISBN":7239,"rating":5.8956895},{"ISBN":5828,"rating":5.8623033},{"ISBN":9714,"rating":5.8586516},{"ISBN":9003,"rating":5.7749743}]}
{"userId":39740,"recommendations":[{"ISBN":9505,"rating":6.407832},{"ISBN":8948,"rating":6.1649523},{"ISBN":7844,"rating":6.098076},{"ISBN":7947,"rating":6.016776},{"ISBN":7869,"rating":5.9831204},{"ISBN":9978,"rating":5.951358},{"ISBN":9897,"rating":5.948019},{"ISBN":9071,"rating":5.941564},{"ISBN":7715,"rating":5.9187465},{"ISBN":9769,"rating":5.8773685}]}
{"userId":39864,"recommendations":[{"ISBN":8548,"rating":5.8646502},{"ISBN":9071,"rating":5.7357254},{"ISBN":7869,"rating":5.672359},{"ISBN":9505,"rating":5.653841},{"ISBN":3491,"rating":5.611453},{"ISBN":7947,"rating":5.594351},{"ISBN":7715,"rating":5.579118},{"ISBN":8946,"rating":5.5777016},{"ISBN":6583,"rating":5.576775},{"ISBN":9932,"rating":5.576357}]}
{"userId":40104,"recommendations":[{"ISBN":6158,"rating":5.8810496},{"ISBN":8501,"rating":5.695123},{"ISBN":4962,"rating":5.5558767},{"ISBN":8284,"rating":5.490299},{"ISBN":7530,"rating":5.4890633},{"ISBN":7494,"rating":5.4670863},{"ISBN":9582,"rating":5.365586},{"ISBN":9131,"rating":5.3545914},{"ISBN":9008,"rating":5.3359036},{"ISBN":2855,"rating":5.3250976}]}
{"userId":40723,"recommendations":[{"ISBN":8956,"rating":6.205668},{"ISBN":7405,"rating":6.0881424},{"ISBN":6522,"rating":6.0732193},{"ISBN":6253,"rating":5.979758},{"ISBN":8854,"rating":5.895924},{"ISBN":6570,"rating":5.8260894},{"ISBN":8118,"rating":5.7832556},{"ISBN":9119,"rating":5.711828},{"ISBN":9008,"rating":5.6424017},{"ISBN":6145,"rating":5.6120644}]}
{"userId":40917,"recommendations":[{"ISBN":9158,"rating":6.41535},{"ISBN":9884,"rating":6.3967223},{"ISBN":8636,"rating":6.1826153},{"ISBN":7844,"rating":6.0002165},{"ISBN":4344,"rating":5.9916687},{"ISBN":8271,"rating":5.9817767},{"ISBN":5593,"rating":5.958123},{"ISBN":7457,"rating":5.9365206},{"ISBN":4715,"rating":5.9199314},{"ISBN":9356,"rating":5.9181013}]}
{"userId":41744,"recommendations":[{"ISBN":8875,"rating":4.831268},{"ISBN":9790,"rating":4.762176},{"ISBN":5731,"rating":4.570758},{"ISBN":9928,"rating":4.564917},{"ISBN":6543,"rating":4.5601244},{"ISBN":8580,"rating":4.5336275},{"ISBN":9360,"rating":4.5236306},{"ISBN":7529,"rating":4.515033},{"ISBN":9923,"rating":4.4955573},{"ISBN":8829,"rating":4.494021}]}
{"userId":41892,"recommendations":[{"ISBN":1935,"rating":6.464648},{"ISBN":9505,"rating":5.591093},{"ISBN":6962,"rating":5.3649955},{"ISBN":8561,"rating":5.353052},{"ISBN":5554,"rating":5.343327},{"ISBN":8338,"rating":5.257445},{"ISBN":9822,"rating":5.254468},{"ISBN":7425,"rating":5.2283735},{"ISBN":6543,"rating":5.2280235},{"ISBN":8648,"rating":5.120211}]}
{"userId":41920,"recommendations":[{"ISBN":9992,"rating":5.598932},{"ISBN":5730,"rating":5.5242915},{"ISBN":5653,"rating":5.3599486},{"ISBN":9534,"rating":5.2800817},{"ISBN":7563,"rating":5.2374887},{"ISBN":7485,"rating":5.2045426},{"ISBN":6917,"rating":5.1880293},{"ISBN":7079,"rating":5.1712413},{"ISBN":9374,"rating":5.109163},{"ISBN":7135,"rating":5.0882487}]}
{"userId":42555,"recommendations":[{"ISBN":8875,"rating":5.271069},{"ISBN":3502,"rating":5.1150055},{"ISBN":5038,"rating":4.976642},{"ISBN":8794,"rating":4.956875},{"ISBN":9850,"rating":4.9233227},{"ISBN":6096,"rating":4.913948},{"ISBN":7337,"rating":4.822423},{"ISBN":8663,"rating":4.783939},{"ISBN":5325,"rating":4.7683315},{"ISBN":7942,"rating":4.739307}]}
{"userId":42648,"recommendations":[{"ISBN":9008,"rating":5.6940455},{"ISBN":6524,"rating":5.504499},{"ISBN":8120,"rating":5.4339614},{"ISBN":1935,"rating":5.30132},{"ISBN":8854,"rating":5.3011985},{"ISBN":9932,"rating":5.2683825},{"ISBN":4107,"rating":5.240834},{"ISBN":2236,"rating":5.2339745},{"ISBN":8338,"rating":5.2247915},{"ISBN":8063,"rating":5.2214785}]}
{"userId":42761,"recommendations":[{"ISBN":9534,"rating":6.414509},{"ISBN":7844,"rating":6.350637},{"ISBN":7988,"rating":6.0699406},{"ISBN":8548,"rating":6.0691185},{"ISBN":7401,"rating":5.9644527},{"ISBN":8604,"rating":5.8833494},{"ISBN":4346,"rating":5.8680024},{"ISBN":6032,"rating":5.8314815},{"ISBN":8571,"rating":5.7690716},{"ISBN":9219,"rating":5.7511396}]}
{"userId":42953,"recommendations":[{"ISBN":9169,"rating":7.17759},{"ISBN":1935,"rating":7.001627},{"ISBN":3479,"rating":6.955742},{"ISBN":9815,"rating":6.7772603},{"ISBN":8007,"rating":6.6797605},{"ISBN":9398,"rating":6.6239777},{"ISBN":9283,"rating":6.4856544},{"ISBN":9399,"rating":6.4173117},{"ISBN":8956,"rating":6.351379},{"ISBN":8732,"rating":6.3229184}]}
{"userId":43664,"recommendations":[{"ISBN":9932,"rating":5.475988},{"ISBN":9815,"rating":5.4563303},{"ISBN":8946,"rating":5.330404},{"ISBN":9516,"rating":5.3028617},{"ISBN":2100,"rating":5.2305326},{"ISBN":8415,"rating":5.1779313},{"ISBN":9992,"rating":5.173774},{"ISBN":5435,"rating":5.145591},{"ISBN":9181,"rating":5.109183},{"ISBN":8703,"rating":5.103976}]}
{"userId":43676,"recommendations":[{"ISBN":9008,"rating":5.5004673},{"ISBN":3628,"rating":5.4141116},{"ISBN":9566,"rating":5.3969765},{"ISBN":862,"rating":5.3696237},{"ISBN":3885,"rating":5.3602095},{"ISBN":7629,"rating":5.347109},{"ISBN":6590,"rating":5.3411517},{"ISBN":7844,"rating":5.328802},{"ISBN":3952,"rating":5.3287916},{"ISBN":6920,"rating":5.308315}]}
{"userId":43743,"recommendations":[{"ISBN":9320,"rating":6.2329416},{"ISBN":953,"rating":5.940122},{"ISBN":9992,"rating":5.8160253},{"ISBN":9008,"rating":5.8017883},{"ISBN":9432,"rating":5.7736955},{"ISBN":936,"rating":5.745393},{"ISBN":6712,"rating":5.68568},{"ISBN":7507,"rating":5.6770062},{"ISBN":1053,"rating":5.6338716},{"ISBN":806,"rating":5.6335855}]}
{"userId":43906,"recommendations":[{"ISBN":9032,"rating":5.119431},{"ISBN":9534,"rating":5.0709634},{"ISBN":3628,"rating":5.0677743},{"ISBN":7337,"rating":5.0438547},{"ISBN":9208,"rating":5.04109},{"ISBN":9566,"rating":4.996866},{"ISBN":8978,"rating":4.9875665},{"ISBN":8548,"rating":4.950536},{"ISBN":6971,"rating":4.940224},{"ISBN":7876,"rating":4.921172}]}
{"userId":43982,"recommendations":[{"ISBN":9322,"rating":5.2108583},{"ISBN":4606,"rating":5.114964},{"ISBN":9345,"rating":5.104777},{"ISBN":6305,"rating":5.0026193},{"ISBN":5454,"rating":4.963306},{"ISBN":9479,"rating":4.9611955},{"ISBN":7842,"rating":4.8904357},{"ISBN":7661,"rating":4.8689046},{"ISBN":7844,"rating":4.8630853},{"ISBN":5906,"rating":4.826075}]}
{"userId":44011,"recommendations":[{"ISBN":7871,"rating":7.72305},{"ISBN":7369,"rating":7.454874},{"ISBN":9497,"rating":6.323215},{"ISBN":9534,"rating":6.270362},{"ISBN":2928,"rating":6.2435565},{"ISBN":9208,"rating":6.2288365},{"ISBN":9982,"rating":6.1391883},{"ISBN":3669,"rating":6.11028},{"ISBN":7955,"rating":6.0792785},{"ISBN":9119,"rating":6.043079}]}
{"userId":44058,"recommendations":[{"ISBN":9534,"rating":6.3819056},{"ISBN":9884,"rating":6.2191963},{"ISBN":9123,"rating":6.04144},{"ISBN":5730,"rating":6.0400968},{"ISBN":9392,"rating":5.859847},{"ISBN":7731,"rating":5.829927},{"ISBN":8403,"rating":5.791772},{"ISBN":7154,"rating":5.7733583},{"ISBN":8611,"rating":5.7660527},{"ISBN":6605,"rating":5.7124624}]}
{"userId":44174,"recommendations":[{"ISBN":5059,"rating":7.016425},{"ISBN":9322,"rating":6.928362},{"ISBN":6570,"rating":6.662188},{"ISBN":9686,"rating":6.5442085},{"ISBN":7754,"rating":6.4740477},{"ISBN":5454,"rating":6.424084},{"ISBN":9347,"rating":6.383018},{"ISBN":9769,"rating":6.3643417},{"ISBN":8368,"rating":6.348687},{"ISBN":9505,"rating":6.2873487}]}
{"userId":44366,"recommendations":[{"ISBN":9008,"rating":6.004584},{"ISBN":9732,"rating":5.944842},{"ISBN":6712,"rating":5.7573433},{"ISBN":8854,"rating":5.5914416},{"ISBN":9650,"rating":5.505695},{"ISBN":8729,"rating":5.4546638},{"ISBN":9714,"rating":5.4018526},{"ISBN":9441,"rating":5.39892},{"ISBN":5447,"rating":5.394698},{"ISBN":2844,"rating":5.3856854}]}
{"userId":44517,"recommendations":[{"ISBN":5059,"rating":5.7423887},{"ISBN":9769,"rating":5.14327},{"ISBN":4157,"rating":5.0469213},{"ISBN":9347,"rating":4.97047},{"ISBN":303,"rating":4.9681873},{"ISBN":8290,"rating":4.9232955},{"ISBN":7754,"rating":4.8644676},{"ISBN":9214,"rating":4.860286},{"ISBN":8616,"rating":4.8288593},{"ISBN":9505,"rating":4.7847695}]}
{"userId":44718,"recommendations":[{"ISBN":7844,"rating":6.2614427},{"ISBN":7401,"rating":6.242069},{"ISBN":9997,"rating":6.1480403},{"ISBN":7364,"rating":6.145567},{"ISBN":3628,"rating":6.0916953},{"ISBN":7947,"rating":6.0708656},{"ISBN":9934,"rating":6.0623474},{"ISBN":5376,"rating":6.0445166},{"ISBN":6751,"rating":6.031575},{"ISBN":2236,"rating":6.0238447}]}
{"userId":45059,"recommendations":[{"ISBN":4154,"rating":5.9174733},{"ISBN":1338,"rating":5.5486374},{"ISBN":9076,"rating":5.355674},{"ISBN":6543,"rating":5.3212366},{"ISBN":9992,"rating":5.288785},{"ISBN":9962,"rating":5.2280765},{"ISBN":9516,"rating":5.2049356},{"ISBN":9307,"rating":5.1617446},{"ISBN":4868,"rating":5.149228},{"ISBN":5208,"rating":5.1387377}]}
{"userId":45313,"recommendations":[{"ISBN":9516,"rating":7.970144},{"ISBN":8703,"rating":7.3837605},{"ISBN":8271,"rating":7.1554027},{"ISBN":8382,"rating":7.1075177},{"ISBN":6639,"rating":7.028079},{"ISBN":9220,"rating":6.999082},{"ISBN":4715,"rating":6.825385},{"ISBN":9815,"rating":6.7798295},{"ISBN":5435,"rating":6.7641816},{"ISBN":5199,"rating":6.6877065}]}
{"userId":45467,"recommendations":[{"ISBN":9347,"rating":5.6217446},{"ISBN":8780,"rating":5.194675},{"ISBN":4518,"rating":5.1598325},{"ISBN":8414,"rating":5.1423182},{"ISBN":8638,"rating":5.1402926},{"ISBN":7844,"rating":5.110198},{"ISBN":8537,"rating":5.104375},{"ISBN":5418,"rating":5.0680313},{"ISBN":8992,"rating":5.0566764},{"ISBN":8408,"rating":4.9939694}]}
{"userId":45571,"recommendations":[{"ISBN":1935,"rating":9.685001},{"ISBN":9988,"rating":8.993164},{"ISBN":8120,"rating":8.601013},{"ISBN":9732,"rating":8.541218},{"ISBN":6215,"rating":8.417979},{"ISBN":8486,"rating":8.312009},{"ISBN":9290,"rating":8.251752},{"ISBN":7756,"rating":8.096897},{"ISBN":9461,"rating":8.092652},{"ISBN":7392,"rating":7.9526467}]}
{"userId":45579,"recommendations":[{"ISBN":6570,"rating":6.8822665},{"ISBN":7129,"rating":6.392223},{"ISBN":5454,"rating":6.2921414},{"ISBN":9768,"rating":6.2828836},{"ISBN":3502,"rating":6.218822},{"ISBN":9203,"rating":6.209528},{"ISBN":7337,"rating":6.2079525},{"ISBN":7837,"rating":6.1749997},{"ISBN":4518,"rating":6.155526},{"ISBN":8513,"rating":6.148365}]}
{"userId":45687,"recommendations":[{"ISBN":9208,"rating":6.251355},{"ISBN":6032,"rating":6.2442102},{"ISBN":6583,"rating":6.0796437},{"ISBN":7947,"rating":6.0699205},{"ISBN":3628,"rating":6.057291},{"ISBN":6400,"rating":6.047674},{"ISBN":8415,"rating":6.0333056},{"ISBN":6312,"rating":6.0323434},{"ISBN":9032,"rating":6.022125},{"ISBN":8639,"rating":6.0096717}]}
{"userId":46581,"recommendations":[{"ISBN":9008,"rating":6.110496},{"ISBN":9551,"rating":5.9449744},{"ISBN":9714,"rating":5.652228},{"ISBN":9997,"rating":5.626004},{"ISBN":5845,"rating":5.56417},{"ISBN":9650,"rating":5.537782},{"ISBN":6524,"rating":5.5145392},{"ISBN":8014,"rating":5.475105},{"ISBN":9934,"rating":5.4690185},{"ISBN":8943,"rating":5.465902}]}
{"userId":47037,"recommendations":[{"ISBN":9008,"rating":6.1776752},{"ISBN":8056,"rating":6.0296516},{"ISBN":6120,"rating":5.996517},{"ISBN":8014,"rating":5.9717813},{"ISBN":9432,"rating":5.83085},{"ISBN":6876,"rating":5.806084},{"ISBN":8326,"rating":5.7892118},{"ISBN":8943,"rating":5.7706223},{"ISBN":9055,"rating":5.7699227},{"ISBN":3628,"rating":5.7695346}]}
{"userId":47583,"recommendations":[{"ISBN":9714,"rating":6.083591},{"ISBN":8259,"rating":5.9100647},{"ISBN":3502,"rating":5.794816},{"ISBN":8907,"rating":5.7762485},{"ISBN":6865,"rating":5.7347436},{"ISBN":8498,"rating":5.694563},{"ISBN":5992,"rating":5.5865073},{"ISBN":7249,"rating":5.562033},{"ISBN":9008,"rating":5.52094},{"ISBN":7900,"rating":5.5058155}]}
{"userId":48070,"recommendations":[{"ISBN":7871,"rating":6.3863034},{"ISBN":3224,"rating":6.3741646},{"ISBN":6224,"rating":6.3635306},{"ISBN":6029,"rating":6.0689135},{"ISBN":9980,"rating":5.932961},{"ISBN":7849,"rating":5.8897457},{"ISBN":9850,"rating":5.8504715},{"ISBN":9265,"rating":5.842833},{"ISBN":9492,"rating":5.823099},{"ISBN":8854,"rating":5.8098574}]}
{"userId":48080,"recommendations":[{"ISBN":5059,"rating":5.604559},{"ISBN":9322,"rating":5.2106714},{"ISBN":7754,"rating":5.2056646},{"ISBN":8616,"rating":5.1757464},{"ISBN":4518,"rating":5.0333433},{"ISBN":6570,"rating":4.9530854},{"ISBN":9347,"rating":4.9355893},{"ISBN":9535,"rating":4.858697},{"ISBN":9105,"rating":4.8363056},{"ISBN":303,"rating":4.8340964}]}
{"userId":48087,"recommendations":[{"ISBN":9762,"rating":9.774932},{"ISBN":6570,"rating":8.324501},{"ISBN":4919,"rating":8.210393},{"ISBN":9322,"rating":8.132394},{"ISBN":5059,"rating":8.047719},{"ISBN":8732,"rating":7.7042723},{"ISBN":7754,"rating":7.6677666},{"ISBN":1697,"rating":7.597723},{"ISBN":8601,"rating":7.5662956},{"ISBN":9283,"rating":7.4730344}]}
{"userId":48166,"recommendations":[{"ISBN":9505,"rating":5.719824},{"ISBN":9011,"rating":5.265833},{"ISBN":8882,"rating":5.2257147},{"ISBN":9076,"rating":5.1952004},{"ISBN":8948,"rating":5.172537},{"ISBN":8946,"rating":5.172212},{"ISBN":9709,"rating":5.0559373},{"ISBN":4411,"rating":5.040429},{"ISBN":6884,"rating":5.0333824},{"ISBN":7947,"rating":5.0288134}]}
{"userId":48204,"recommendations":[{"ISBN":8368,"rating":8.106877},{"ISBN":9492,"rating":8.086323},{"ISBN":5059,"rating":7.893549},{"ISBN":8200,"rating":7.7333593},{"ISBN":3479,"rating":7.707904},{"ISBN":9203,"rating":7.5602436},{"ISBN":8382,"rating":7.395725},{"ISBN":6570,"rating":7.372339},{"ISBN":8703,"rating":7.268856},{"ISBN":8271,"rating":7.159764}]}
{"userId":48483,"recommendations":[{"ISBN":5845,"rating":7.0557184},{"ISBN":9553,"rating":6.54092},{"ISBN":8548,"rating":6.538216},{"ISBN":9551,"rating":6.531187},{"ISBN":9322,"rating":6.5287476},{"ISBN":9283,"rating":6.490968},{"ISBN":9003,"rating":6.362913},{"ISBN":7754,"rating":6.337249},{"ISBN":9008,"rating":6.1819696},{"ISBN":6583,"rating":6.1527176}]}
{"userId":48492,"recommendations":[{"ISBN":8580,"rating":6.589314},{"ISBN":9505,"rating":6.105683},{"ISBN":9978,"rating":6.08042},{"ISBN":4783,"rating":6.001541},{"ISBN":6543,"rating":5.9809427},{"ISBN":8948,"rating":5.935274},{"ISBN":5454,"rating":5.9013453},{"ISBN":9360,"rating":5.896218},{"ISBN":8455,"rating":5.8834195},{"ISBN":7947,"rating":5.873791}]}
{"userId":48922,"recommendations":[{"ISBN":8580,"rating":5.885531},{"ISBN":9345,"rating":5.7008142},{"ISBN":8946,"rating":5.6821227},{"ISBN":9578,"rating":5.6478634},{"ISBN":8948,"rating":5.471899},{"ISBN":5454,"rating":5.4683146},{"ISBN":7844,"rating":5.416641},{"ISBN":8996,"rating":5.3977227},{"ISBN":4783,"rating":5.3932643},{"ISBN":7110,"rating":5.3731403}]}
{"userId":49033,"recommendations":[{"ISBN":9051,"rating":6.192422},{"ISBN":9982,"rating":6.137797},{"ISBN":8616,"rating":5.9102225},{"ISBN":8638,"rating":5.8175163},{"ISBN":8408,"rating":5.772497},{"ISBN":8458,"rating":5.7453403},{"ISBN":7554,"rating":5.731891},{"ISBN":5892,"rating":5.7077622},{"ISBN":5418,"rating":5.6583285},{"ISBN":9260,"rating":5.638432}]}
{"userId":49083,"recommendations":[{"ISBN":8875,"rating":6.2422094},{"ISBN":9220,"rating":6.0318313},{"ISBN":7104,"rating":5.8529773},{"ISBN":8946,"rating":5.7909427},{"ISBN":7715,"rating":5.7810583},{"ISBN":9790,"rating":5.7539563},{"ISBN":6583,"rating":5.6507792},{"ISBN":8200,"rating":5.5930567},{"ISBN":3479,"rating":5.5890393},{"ISBN":7754,"rating":5.567239}]}
{"userId":49142,"recommendations":[{"ISBN":7871,"rating":8.29871},{"ISBN":7369,"rating":8.294843},{"ISBN":3224,"rating":7.0996666},{"ISBN":9850,"rating":7.0812387},{"ISBN":6145,"rating":6.9752374},{"ISBN":6224,"rating":6.5436726},{"ISBN":9492,"rating":6.439723},{"ISBN":8382,"rating":6.4293184},{"ISBN":9548,"rating":6.408648},{"ISBN":7560,"rating":6.364049}]}
{"userId":49279,"recommendations":[{"ISBN":1935,"rating":9.865915},{"ISBN":9392,"rating":7.424842},{"ISBN":6312,"rating":7.3763657},{"ISBN":9534,"rating":7.179121},{"ISBN":9290,"rating":7.1116076},{"ISBN":9461,"rating":6.817294},{"ISBN":4940,"rating":6.606593},{"ISBN":6419,"rating":6.577527},{"ISBN":9208,"rating":6.5692124},{"ISBN":6971,"rating":6.5505304}]}
{"userId":49304,"recommendations":[{"ISBN":9008,"rating":6.3039603},{"ISBN":5845,"rating":5.9634724},{"ISBN":6583,"rating":5.775168},{"ISBN":7401,"rating":5.7140217},{"ISBN":8639,"rating":5.6954217},{"ISBN":8854,"rating":5.68659},{"ISBN":9529,"rating":5.642547},{"ISBN":9551,"rating":5.6249948},{"ISBN":6524,"rating":5.6235847},{"ISBN":8879,"rating":5.566185}]}
{"userId":49407,"recommendations":[{"ISBN":9260,"rating":7.2344685},{"ISBN":6893,"rating":6.8239355},{"ISBN":9051,"rating":6.661427},{"ISBN":8479,"rating":6.379618},{"ISBN":8358,"rating":6.315897},{"ISBN":8601,"rating":6.251183},{"ISBN":3479,"rating":6.136245},{"ISBN":4150,"rating":6.1023245},{"ISBN":3880,"rating":6.0872655},{"ISBN":6599,"rating":6.074226}]}
{"userId":49470,"recommendations":[{"ISBN":8946,"rating":5.6125956},{"ISBN":8580,"rating":5.586452},{"ISBN":9320,"rating":5.5703473},{"ISBN":9004,"rating":5.5527706},{"ISBN":6772,"rating":5.5386376},{"ISBN":9432,"rating":5.481468},{"ISBN":1121,"rating":5.4007726},{"ISBN":8249,"rating":5.391731},{"ISBN":9992,"rating":5.3916707},{"ISBN":4202,"rating":5.3902454}]}
{"userId":49811,"recommendations":[{"ISBN":3224,"rating":6.9034142},{"ISBN":7871,"rating":6.36446},{"ISBN":6224,"rating":6.324106},{"ISBN":8854,"rating":6.315482},{"ISBN":6029,"rating":6.0182257},{"ISBN":6712,"rating":6.0165534},{"ISBN":9492,"rating":6.015354},{"ISBN":9265,"rating":5.933332},{"ISBN":9980,"rating":5.929629},{"ISBN":7849,"rating":5.8496585}]}
{"userId":50881,"recommendations":[{"ISBN":9516,"rating":7.469341},{"ISBN":7871,"rating":7.3192835},{"ISBN":3479,"rating":6.768778},{"ISBN":9815,"rating":6.649004},{"ISBN":9193,"rating":6.489353},{"ISBN":5897,"rating":6.406437},{"ISBN":8382,"rating":6.3997264},{"ISBN":4262,"rating":6.2835464},{"ISBN":8034,"rating":6.278915},{"ISBN":6753,"rating":6.214195}]}
{"userId":50920,"recommendations":[{"ISBN":7844,"rating":5.795688},{"ISBN":7947,"rating":5.6917863},{"ISBN":8636,"rating":5.590845},{"ISBN":8946,"rating":5.523329},{"ISBN":8580,"rating":5.497158},{"ISBN":7063,"rating":5.485364},{"ISBN":287,"rating":5.4777718},{"ISBN":9843,"rating":5.46835},{"ISBN":9010,"rating":5.4672956},{"ISBN":8548,"rating":5.463873}]}
{"userId":51202,"recommendations":[{"ISBN":9290,"rating":6.923282},{"ISBN":1935,"rating":6.8475246},{"ISBN":6312,"rating":6.634191},{"ISBN":7482,"rating":6.4150443},{"ISBN":8522,"rating":6.3931546},{"ISBN":9516,"rating":6.393066},{"ISBN":9962,"rating":5.967458},{"ISBN":7581,"rating":5.933217},{"ISBN":7369,"rating":5.6715894},{"ISBN":9110,"rating":5.619449}]}
{"userId":51330,"recommendations":[{"ISBN":9220,"rating":4.9144125},{"ISBN":9568,"rating":4.9107485},{"ISBN":8946,"rating":4.881413},{"ISBN":9516,"rating":4.784251},{"ISBN":6077,"rating":4.7530227},{"ISBN":5208,"rating":4.7349195},{"ISBN":5435,"rating":4.65083},{"ISBN":9181,"rating":4.630436},{"ISBN":6639,"rating":4.580055},{"ISBN":9962,"rating":4.556384}]}
{"userId":51385,"recommendations":[{"ISBN":7844,"rating":5.8268747},{"ISBN":8559,"rating":5.7862506},{"ISBN":8948,"rating":5.6428285},{"ISBN":9441,"rating":5.491643},{"ISBN":4344,"rating":5.4644227},{"ISBN":8636,"rating":5.4525614},{"ISBN":9260,"rating":5.4485025},{"ISBN":9356,"rating":5.423632},{"ISBN":8239,"rating":5.4150014},{"ISBN":9545,"rating":5.4077597}]}
{"userId":51597,"recommendations":[{"ISBN":9008,"rating":5.8381224},{"ISBN":6712,"rating":5.5362024},{"ISBN":6583,"rating":5.439469},{"ISBN":9932,"rating":5.4047103},{"ISBN":5919,"rating":5.3964486},{"ISBN":6425,"rating":5.363223},{"ISBN":2844,"rating":5.353907},{"ISBN":9441,"rating":5.3247952},{"ISBN":6613,"rating":5.3015103},{"ISBN":8643,"rating":5.2749243}]}
{"userId":51681,"recommendations":[{"ISBN":9516,"rating":6.920363},{"ISBN":9815,"rating":6.8952155},{"ISBN":9568,"rating":6.3872924},{"ISBN":9438,"rating":6.2472258},{"ISBN":5435,"rating":6.2463307},{"ISBN":9193,"rating":6.239372},{"ISBN":7438,"rating":6.2154293},{"ISBN":4898,"rating":6.1873293},{"ISBN":5208,"rating":6.133085},{"ISBN":8946,"rating":6.126507}]}
{"userId":51934,"recommendations":[{"ISBN":9709,"rating":6.3054338},{"ISBN":9011,"rating":5.671122},{"ISBN":3502,"rating":5.6292796},{"ISBN":9345,"rating":5.615079},{"ISBN":9441,"rating":5.6057534},{"ISBN":4783,"rating":5.5694704},{"ISBN":6591,"rating":5.5311017},{"ISBN":7837,"rating":5.4568233},{"ISBN":7881,"rating":5.4513316},{"ISBN":7039,"rating":5.4512343}]}
{"userId":52010,"recommendations":[{"ISBN":9997,"rating":5.99198},{"ISBN":9008,"rating":5.9896374},{"ISBN":9714,"rating":5.8147697},{"ISBN":7881,"rating":5.6519346},{"ISBN":9624,"rating":5.6004763},{"ISBN":9324,"rating":5.537373},{"ISBN":4755,"rating":5.5180664},{"ISBN":7264,"rating":5.513077},{"ISBN":9003,"rating":5.4594374},{"ISBN":9004,"rating":5.4537573}]}
{"userId":52023,"recommendations":[{"ISBN":7485,"rating":5.9589257},{"ISBN":4202,"rating":5.8668756},{"ISBN":1657,"rating":5.856607},{"ISBN":6169,"rating":5.775152},{"ISBN":7496,"rating":5.761171},{"ISBN":8259,"rating":5.7540584},{"ISBN":8232,"rating":5.664628},{"ISBN":8238,"rating":5.6503415},{"ISBN":6917,"rating":5.6182585},{"ISBN":8611,"rating":5.5760155}]}
{"userId":52255,"recommendations":[{"ISBN":9831,"rating":9.11039},{"ISBN":8519,"rating":8.920549},{"ISBN":9534,"rating":8.350435},{"ISBN":5094,"rating":8.219086},{"ISBN":9505,"rating":8.141953},{"ISBN":7869,"rating":8.003439},{"ISBN":9418,"rating":7.81296},{"ISBN":9769,"rating":7.781558},{"ISBN":4936,"rating":7.764829},{"ISBN":8069,"rating":7.7379265}]}
{"userId":52472,"recommendations":[{"ISBN":9505,"rating":6.062128},{"ISBN":9008,"rating":5.837437},{"ISBN":7789,"rating":5.750512},{"ISBN":9441,"rating":5.745537},{"ISBN":9347,"rating":5.7314796},{"ISBN":7009,"rating":5.6518245},{"ISBN":8561,"rating":5.646908},{"ISBN":5454,"rating":5.64441},{"ISBN":8998,"rating":5.640408},{"ISBN":6712,"rating":5.618023}]}
{"userId":52870,"recommendations":[{"ISBN":7871,"rating":7.0454493},{"ISBN":6224,"rating":6.934804},{"ISBN":4845,"rating":6.6078596},{"ISBN":9732,"rating":6.6030726},{"ISBN":9980,"rating":6.5794864},{"ISBN":6712,"rating":6.5272303},{"ISBN":7849,"rating":6.519922},{"ISBN":4809,"rating":6.491938},{"ISBN":6613,"rating":6.484216},{"ISBN":5953,"rating":6.4428096}]}
{"userId":53080,"recommendations":[{"ISBN":7754,"rating":5.594696},{"ISBN":5059,"rating":5.4258604},{"ISBN":9322,"rating":5.3974767},{"ISBN":9158,"rating":5.3581696},{"ISBN":5593,"rating":5.0548387},{"ISBN":8854,"rating":4.9899573},{"ISBN":8956,"rating":4.968808},{"ISBN":9363,"rating":4.9600525},{"ISBN":9294,"rating":4.95102},{"ISBN":8314,"rating":4.902959}]}
